user/src/basic/qdiv.v
`ifndef QDIV_V
`define QDIV_V

module qdiv(
    input clk,
    input rst_n,
    input [31:0] dividend,
    input [31:0] divisor,
    output reg [31:0] quotient,
    output reg valid,//运算完成信号
    output reg warn,//除数为0警告
    output reg busy//运算中信号
    );

    parameter WIDTH = 31;
    parameter  FBITS = 16;

    wire [WIDTH-1:0] dividend_unsigned;
    wire [WIDTH-1:0] divisor_unsigned;

    integer i=0;

    reg [WIDTH-1:0] dividend_reg;//被除数寄存器(不带符号)
    reg [WIDTH-1:0] divisor_reg;//除数寄存器(不带符号)
    reg [WIDTH:0] acc;//单次被除数
    reg [WIDTH-1:0] quo;//实际使用中移位的被除数和商(复用)

    reg [WIDTH:0] acc_next;//单次被除数下一个
    reg [WIDTH-1:0] quo_next;//实际使用中移位的被除数下一个

    assign dividend_unsigned=dividend[WIDTH-1:0];
    assign divisor_unsigned=divisor[WIDTH-1:0];

    always @(*) 
    begin
      if (acc >= {1'b0, divisor_reg}) 
      begin
        acc_next = acc - divisor_reg;
        {acc_next, quo_next} = {acc_next[WIDTH-1:0], quo, 1'b1};
      end 
      else 
      begin
        {acc_next, quo_next} = {acc, quo} << 1;
      end
    end

    always @(posedge clk or negedge rst_n) 
    begin
        if(!rst_n)
        begin
            dividend_reg <= 0;
            divisor_reg <= 0;
            quotient <= 0;
            valid <= 0;
            warn <= 0;
            acc <= 0;
            quo <= 0;
            busy <= 0;

            //acc_next <= 0;
            //quo_next <= 0;
        end
        else if(divisor==0)
        begin
            warn <= 1;
            valid <= 0;
            quotient <= 0;
            busy <= 0;
        end
        else
        begin
            dividend_reg <= dividend_unsigned;
            divisor_reg <= divisor_unsigned;
            if(dividend_unsigned!=dividend_reg||divisor_unsigned!=divisor_reg)//输入变化，重新计算
            begin
                i <= 0;
                valid <= 0;
                {acc, quo} <= {{WIDTH{1'b0}}, dividend_unsigned, 1'b0};
                busy <= 1'b1;
            end
            else
            begin
                if(i==WIDTH+FBITS-1)
                begin
                    valid<=1;
                    busy <= 1'b0;
                    if(dividend[WIDTH]==divisor[WIDTH])
                      quotient<={1'b0,quo_next[WIDTH-1:0]};
                    else
                      quotient<={1'b1,quo_next[WIDTH-1:0]};
                end
                else
                begin
                    i<=i+1;
                    {acc, quo} <= {acc_next, quo_next};
                end
            end
        end
    end
endmodule
`endif

user/src/basic/qadd.v
//小数加法器，32位数据，31位为符号位，30-16位为整数位，15-0位为小数位
//输入：加数32位的add1,add2
//输出：和数32位的sum
`ifndef QADD_V
`define QADD_V
module qadd
(
    input [31:0] add1,
    input [31:0] add2,
    output [31:0] sum
);
    reg[31:0] res=0;//暂存加的结果

    assign sum = res;

    always @(*) 
    begin
        if(add1[31]==add2[31])//同号相加
        begin
            res[31] = add1[31];
            if(add1[30:0]+add2[30:0]>=2**31)//判断是否溢出
            begin
                res[30:0] = add1[30:0]+add2[30:0]-2**31;
            end
            else
            begin
                res[30:0] = add1[30:0]+add2[30:0];
            end
        end
        else//异号则数字位相减
        begin
            if(add1[30:0]>add2[30:0])
            begin
                res[31] = add1[31];
                res[30:0] = add1[30:0]-add2[30:0];
            end
            else if(add1[30:0]<add2[30:0])
            begin
                res[31] = add2[31];
                res[30:0] = add2[30:0]-add1[30:0];
            end
            else
            begin
                res[31] = 1'b0;
                res[30:0] = 0;
            end
        end
    end
endmodule
`endif

user/src/basic/sqrt.v
//`include "../qmulti/qmulti.v"
//`include "../qdiv/qdiv.v"
//`include "../qadd/qadd.v"
`ifndef SQRT_V
`define SQRT_V
module sqrt(
    input clk,
    input rst_n,
    output reg valid,

    input [31:0] sqrter,
    output reg [31:0] sqrted
);

    wire [31:0] iter;
    wire [31:0] two;
    wire [31:0] dived;
    wire [31:0] sum;
    wire [31:0] iter_next;
    wire valid_dived;

    reg [31:0] sqrter_reg;
    reg [31:0] iter_reg;

    integer i=0;
    
    assign iter = iter_reg;
    assign iter_next = sum>>1;

    qdiv 
    qdiv_dut1 (
        .clk (clk ),
        .rst_n (rst_n ),
        .valid(valid_dived),
        .busy(),
        .dividend (sqrter ),
        .divisor (iter ),
        .quotient (dived ),
        .warn  ( )
    );
    qadd
    qadd_dut (
        .add1 (dived ),
        .add2 (iter ),
        .sum (sum )
    );

    always @(posedge clk or negedge rst_n) 
    begin
        if(rst_n==0)
        begin
            sqrter_reg <= 0;
            sqrted <= 0;
            i <= 0;
            valid <= 0;
            iter_reg <= 0;
        end
        else
        begin
            sqrter_reg <= sqrter;
            if(sqrter_reg != sqrter)
            begin
                i <= 0;
                iter_reg <= sqrter;
                valid <= 0;
            end
            else if(i == 21)
            begin
                sqrted <= iter;
                valid <= 1;
            end
            else
            begin
                if(valid_dived)
                begin
                    iter_reg <= iter_next;
                    i <= i+1;
                end
            end
        end
    end

endmodule
`endif

user/src/basic/qmulti.v
`ifndef QMULTI_V
`define QMULTI_V
module qmulti(
    input [31:0] multi1,
    input [31:0] multi2,
    output [31:0] result
);

reg [63:0] tmp=0;
reg [31:0] result_out=0;

assign result=result_out;

always @(*) 
begin
    tmp=multi1[30:0]*multi2[30:0];
    if(multi1[31]==multi2[31])
    begin
        result_out={1'b0,tmp[46:16]};
    end
    else
    begin
        result_out={1'b1,tmp[46:16]};
    end
end

endmodule
`endif

user/src/basic/xita_tan_lut.v
//θ-tanθ查找表模块
//输入：i（tanθ=1/2^i）（迭代次数）
//输出：θ（角度值）
//功能：输入1/2^i即tanθ，输出θ（角度值）
`ifndef XITA_TAN_LUT_V
`define XITA_TAN_LUT_V
module xita_tan_lut(
    input clk,
    input [4:0]i,
    output reg [31:0] xita
);
    
    always @(posedge clk) 
    begin
        case(i)
        0: begin
            xita[31:16]=45;
            xita[15:0]=0;
        end
        1: begin
            xita[31:16]=26;
            xita[15:0]=37031;
        end
        2: begin
            xita[31:16]=14;
            xita[15:0]=2375;
        end
        3: begin
            xita[30:16]=7;
            xita[15:0]=8193;
        end
        4: begin
            xita[31:16]=3;
            xita[15:0]=37770;
        end
        5: begin
            xita[31:16]=1;
            xita[15:0]=51767;
        end
        6: begin
            xita[31:16]=0;
            xita[15:0]=58666;
        end
        7: begin
            xita[31:16]=0;
            xita[15:0]=29334;
        end
        8: begin
            xita[31:16]=0;
            xita[15:0]=14667;
        end
        9: begin
            xita[31:16]=0;
            xita[15:0]=7333;
        end
        10: begin
            xita[31:16]=0;
            xita[15:0]=3666;
        end
        11: begin
            xita[31:16]=0;
            xita[15:0]=1833;
        end
        12: begin
            xita[31:16]=0;
            xita[15:0]=916;
        end
        13: begin
            xita[31:16]=0;
            xita[15:0]=458;
        end
        14: begin
            xita[31:16]=0;
            xita[15:0]=229;
        end
        15: begin
            xita[31:16]=0;
            xita[15:0]=114;
        end
        16: begin
            xita[31:16]=0;
            xita[15:0]=57;
        end
        17: begin
            xita[31:16]=0;
            xita[15:0]=28;
        end
        18: begin
            xita[31:16]=0;
            xita[15:0]=14;
        end
        19: begin
            xita[31:16]=0;
            xita[15:0]=7;
        end
        20: begin
            xita[31:16]=0;
            xita[15:0]=4;
        end
        default : xita=0;    
        endcase
    end

endmodule
`endif

user/src/basic/tan.v
`ifndef TAN_V
`define TAN_V
//`include "../arctan/xita_tan_lut.v"
//`include "../qdiv/qdiv.v"
module tan(
    input clk,
    input rst_n,
    output reg valid,

    input [31:0] xita,
    output reg [31:0] tan
);

    parameter K=39796;

    wire valid_div;
    wire [31:0] tan_c;//当前正切值
    wire [31:0] xita_c;//当前旋转角

    reg [31:0] x;
    reg [31:0] y;
    reg [31:0] z;
    reg [31:0] xita_reg;
    reg [1:0] cnt;

    integer i=0;

    qdiv 
    qdiv_dut (
        .clk (clk ),
        .rst_n (rst_n ),
        .valid ( valid_div),
        .dividend (y ),
        .divisor (x ),
        .quotient (tan_c ),
        .warn ( ),
        .busy ( )
    );
    xita_tan_lut 
    xita_tan_lut_dut (
        .clk(clk ),
        .i (i ),
        .xita  ( xita_c)
    );

    always @(posedge clk or negedge rst_n) 
    begin
        if(!rst_n)
        begin
            valid<=0;
            x<=0;
            y<=0;
            z<=0;
            i<=0;
            xita_reg<=xita;
            tan<=0;
            cnt<=0;
        end
        else
        begin
            xita_reg<=xita;
            if(xita_reg!=xita)
            begin
                i<=0;
                x<=K;
                y<=0;
                z<=0;
                valid<=0;
                cnt<=0;
            end
            else
            begin
                if(i==20)
                begin
                    valid<=1;
                    tan<=tan_c;
                    cnt<=0;
                end
                else
                begin
                    if(valid_div==1)
                    begin
                       cnt<=cnt+1;
                    end
                    else
                    begin
                        cnt<=0;
                    end
                    if(valid_div==1 && cnt==2)
                    begin
                        i<=i+1;
                        if(z<xita)
                        begin
                            z<=z+xita_c;
                            x<=x-(y>>i);
                            y<=y+(x>>i);
                        end
                        else if(z>xita)
                        begin
                            z<=z-xita_c;
                            x<=x+(y>>i);
                            y<=y-(x>>i);
                        end
                        else
                        begin
                            z<=z;
                            x<=x;
                            y<=y;
                        end
                    end
                end
            end
        end      
    end

endmodule
`endif

user/src/basic/cos.v
`ifndef COS_V
`define COS_V

//`include "../tan/tan.v"
//`include "../qdiv/qdiv.v"
//`include "../qmulti/qmulti.v"
//`include "../qadd/qadd.v"
//`include "../sqrt/sqrt.v"
//`include "../arctan/xita_tan_lut.v"
module cos(
    input [31:0] clk,
    input [31:0] rst_n,
    output reg valid,

    input [31:0] xita,
    output reg [31:0] cos
);
    wire [31:0] tan;
    wire [31:0] tan_2;
    wire [31:0] tan_2_add_1;
    wire [31:0] deno;
    wire valid_tan;
    wire valid_sqrt;
    wire valid_qdiv;
    wire [31:0] cos_sharp;

    reg [31:0] xita_reg;
    reg [31:0] tan_2_add_1_reg;
    reg [31:0] deno_reg;
    reg valid_tan_prev;
    reg valid_sqrt_prev;
    reg valid_qdiv_prev;

    tan 
    tan_dut (
      .clk  (clk ),
      .rst_n  (rst_n ),
      .valid  (valid_tan ),
      .xita (xita_reg ),
      .tan  ( tan)
    );
    qmulti
    qmulti_dut (
      .multi1 (tan ),
      .multi2 (tan ),
      .result  ( tan_2)
    );
    qadd
    qadd_dut (
      .add1 (tan_2 ),
      .add2 (32'h0001_0000 ),
      .sum  ( tan_2_add_1)
    );
    sqrt
    sqrt_dut (
      .clk  (clk ),
      .rst_n  (rst_n ),
      .valid  (valid_sqrt ),
      .sqrter (tan_2_add_1_reg ),
      .sqrted ( deno)
    );
    qdiv
    qdiv_dut (
      .clk  (clk ),
      .rst_n  (rst_n ),
      .valid  (valid_qdiv ),
      .busy  ( ),
      .dividend (32'h0001_0000 ),
      .divisor (deno_reg ),
      .quotient  ( cos_sharp),
      .warn  ( )
    );

    always @(posedge clk or negedge rst_n) 
    begin
      if(!rst_n)
      begin
        valid <= 1'b0;
        xita_reg<=0;
        tan_2_add_1_reg<=0;
        deno_reg<=0;
        valid_tan_prev<=0;
        valid_sqrt_prev<=0;
        valid_qdiv_prev<=0;
        cos <= 32'h0000_0000;
      end
      else
      begin
        xita_reg <= xita;
        valid_tan_prev <= valid_tan;
        valid_sqrt_prev <= valid_sqrt;
        valid_qdiv_prev <= valid_qdiv;
        if(xita_reg!=xita)
        begin
          valid <= 1'b0;
        end
        else
        begin
          if(valid_tan_prev==1'b0 && valid_tan==1'b1)
          begin
            tan_2_add_1_reg <= tan_2_add_1;
          end

          if(valid_sqrt_prev==1'b0 && valid_sqrt==1'b1)
          begin
            deno_reg <= deno;
          end

          if(valid_qdiv_prev==1'b0 && valid_qdiv==1'b1)
          begin
            valid <= 1'b1;
            cos <= cos_sharp;
          end
        end
      end
    end
endmodule
`endif

user/sim/basic/cos_tb.v
`timescale 1ns/1ps
module cos_tb;

// Parameters

// Ports
reg [31:0] clk;
reg [31:0] rst_n;
wire valid;
reg [31:0] xita;
wire [31:0] cos;

cos 
cos_dut (
  .clk (clk ),
  .rst_n (rst_n ),
  .valid (valid ),
  .xita (xita ),
  .cos  ( cos)
);

initial begin
  begin
      $dumpfile("cos_tb.vcd");
      $dumpvars(0, cos_tb);
      clk=0;
      rst_n=1;
      #10
      rst_n=0;
      #10
      rst_n=1;
      #10
      xita=0;
      #10000
      xita=32'h001E_0000;
      #10000
      xita=32'h003C_0000;
      #10000
      xita=32'h002D_0000;
      #10000
      xita=0;
      #10000
    $finish;
  end
end

always
  #1  clk = ! clk ;

endmodule

cos_tb.vcd
$date
	Tue Jul 04 10:45:56 2023
$end
$version
	Icarus Verilog
$end
$timescale
	1ps
$end
$scope module cos_tb $end
$var wire 1 ! valid $end
$var wire 32 " cos [31:0] $end
$var reg 32 # clk [31:0] $end
$var reg 32 $ rst_n [31:0] $end
$var reg 32 % xita [31:0] $end
$scope module cos_dut $end
$var wire 32 & clk [31:0] $end
$var wire 32 ' rst_n [31:0] $end
$var wire 32 ( xita [31:0] $end
$var wire 1 ) valid_tan $end
$var wire 1 * valid_sqrt $end
$var wire 1 + valid_qdiv $end
$var wire 32 , tan_2_add_1 [31:0] $end
$var wire 32 - tan_2 [31:0] $end
$var wire 32 . tan [31:0] $end
$var wire 32 / deno [31:0] $end
$var wire 32 0 cos_sharp [31:0] $end
$var reg 32 1 cos [31:0] $end
$var reg 32 2 deno_reg [31:0] $end
$var reg 32 3 tan_2_add_1_reg [31:0] $end
$var reg 1 ! valid $end
$var reg 1 4 valid_qdiv_prev $end
$var reg 1 5 valid_sqrt_prev $end
$var reg 1 6 valid_tan_prev $end
$var reg 32 7 xita_reg [31:0] $end
$scope module qadd_dut $end
$var wire 32 8 add2 [31:0] $end
$var wire 32 9 sum [31:0] $end
$var wire 32 : add1 [31:0] $end
$var reg 32 ; res [31:0] $end
$upscope $end
$scope module qdiv_dut $end
$var wire 1 < clk $end
$var wire 32 = dividend [31:0] $end
$var wire 32 > divisor [31:0] $end
$var wire 1 ? rst_n $end
$var wire 31 @ divisor_unsigned [30:0] $end
$var wire 31 A dividend_unsigned [30:0] $end
$var parameter 32 B FBITS $end
$var parameter 32 C WIDTH $end
$var reg 32 D acc [31:0] $end
$var reg 32 E acc_next [31:0] $end
$var reg 1 F busy $end
$var reg 31 G dividend_reg [30:0] $end
$var reg 31 H divisor_reg [30:0] $end
$var reg 31 I quo [30:0] $end
$var reg 31 J quo_next [30:0] $end
$var reg 32 K quotient [31:0] $end
$var reg 1 + valid $end
$var reg 1 L warn $end
$var integer 32 M i [31:0] $end
$upscope $end
$scope module qmulti_dut $end
$var wire 32 N result [31:0] $end
$var wire 32 O multi2 [31:0] $end
$var wire 32 P multi1 [31:0] $end
$var reg 32 Q result_out [31:0] $end
$var reg 64 R tmp [63:0] $end
$upscope $end
$scope module sqrt_dut $end
$var wire 1 S clk $end
$var wire 1 T rst_n $end
$var wire 32 U sqrter [31:0] $end
$var wire 1 V valid_dived $end
$var wire 32 W sum [31:0] $end
$var wire 32 X iter_next [31:0] $end
$var wire 32 Y iter [31:0] $end
$var wire 32 Z dived [31:0] $end
$var reg 32 [ iter_reg [31:0] $end
$var reg 32 \ sqrted [31:0] $end
$var reg 32 ] sqrter_reg [31:0] $end
$var reg 1 * valid $end
$var integer 32 ^ i [31:0] $end
$scope module qadd_dut $end
$var wire 32 _ add2 [31:0] $end
$var wire 32 ` sum [31:0] $end
$var wire 32 a add1 [31:0] $end
$var reg 32 b res [31:0] $end
$upscope $end
$scope module qdiv_dut1 $end
$var wire 1 S clk $end
$var wire 32 c dividend [31:0] $end
$var wire 32 d divisor [31:0] $end
$var wire 1 T rst_n $end
$var wire 31 e divisor_unsigned [30:0] $end
$var wire 31 f dividend_unsigned [30:0] $end
$var parameter 32 g FBITS $end
$var parameter 32 h WIDTH $end
$var reg 32 i acc [31:0] $end
$var reg 32 j acc_next [31:0] $end
$var reg 1 k busy $end
$var reg 31 l dividend_reg [30:0] $end
$var reg 31 m divisor_reg [30:0] $end
$var reg 31 n quo [30:0] $end
$var reg 31 o quo_next [30:0] $end
$var reg 32 p quotient [31:0] $end
$var reg 1 V valid $end
$var reg 1 q warn $end
$var integer 32 r i [31:0] $end
$upscope $end
$upscope $end
$scope module tan_dut $end
$var wire 1 s clk $end
$var wire 1 t rst_n $end
$var wire 32 u xita [31:0] $end
$var wire 32 v xita_c [31:0] $end
$var wire 1 w valid_div $end
$var wire 32 x tan_c [31:0] $end
$var parameter 32 y K $end
$var reg 2 z cnt [1:0] $end
$var reg 32 { tan [31:0] $end
$var reg 1 ) valid $end
$var reg 32 | x [31:0] $end
$var reg 32 } xita_reg [31:0] $end
$var reg 32 ~ y [31:0] $end
$var reg 32 !" z [31:0] $end
$var integer 32 "" i [31:0] $end
$scope module qdiv_dut $end
$var wire 1 s clk $end
$var wire 32 #" dividend [31:0] $end
$var wire 32 $" divisor [31:0] $end
$var wire 1 t rst_n $end
$var wire 31 %" divisor_unsigned [30:0] $end
$var wire 31 &" dividend_unsigned [30:0] $end
$var parameter 32 '" FBITS $end
$var parameter 32 (" WIDTH $end
$var reg 32 )" acc [31:0] $end
$var reg 32 *" acc_next [31:0] $end
$var reg 1 +" busy $end
$var reg 31 ," dividend_reg [30:0] $end
$var reg 31 -" divisor_reg [30:0] $end
$var reg 31 ." quo [30:0] $end
$var reg 31 /" quo_next [30:0] $end
$var reg 32 0" quotient [31:0] $end
$var reg 1 w valid $end
$var reg 1 1" warn $end
$var integer 32 2" i [31:0] $end
$upscope $end
$scope module xita_tan_lut_dut $end
$var wire 1 s clk $end
$var wire 5 3" i [4:0] $end
$var reg 32 4" xita [31:0] $end
$upscope $end
$upscope $end
$upscope $end
$upscope $end
$enddefinitions $end
$comment Show the parameter values. $end
$dumpall
b11111 ("
b10000 '"
b1001101101110100 y
b11111 h
b10000 g
b11111 C
b10000 B
$end
#0
$dumpvars
b1011010000000000000000 4"
b0 3"
b0 2"
x1"
bx 0"
bx /"
bx ."
bx -"
bx ,"
x+"
bx *"
bx )"
bx &"
bx %"
bx $"
bx #"
b0 ""
bx !"
bx ~
bx }
bx |
bx {
b0 z
bx x
xw
b1011010000000000000000 v
bx u
1t
0s
b0 r
xq
bx p
bx o
bx n
bx m
bx l
xk
bx j
bx i
bx f
bx e
bx d
bx c
b0 b
bx a
b0 `
bx _
b0 ^
bx ]
bx \
bx [
bx Z
bx Y
b0 X
b0 W
xV
bx U
1T
0S
b0 R
b0 Q
bx P
bx O
b0 N
b0 M
xL
bx K
bx J
bx I
bx H
bx G
xF
bx E
bx D
b10000000000000000 A
bx @
1?
bx >
b10000000000000000 =
0<
b10000000000000000 ;
b0 :
b10000000000000000 9
b10000000000000000 8
bx 7
x6
x5
x4
bx 3
bx 2
bx 1
bx 0
bx /
bx .
b0 -
b10000000000000000 ,
x+
x*
x)
bx (
b1 '
b0 &
bx %
b1 $
b0 #
bx "
x!
$end
#1000
b1 2"
b1 r
b1 M
b10000000000000000 G
1s
1S
1<
b1 #
b1 &
#2000
0s
0S
0<
b0 #
b0 &
#3000
b10 2"
b10 r
b10 M
1s
1S
1<
b1 #
b1 &
#4000
0s
0S
0<
b0 #
b0 &
#5000
b11 2"
b11 r
b11 M
1s
1S
1<
b1 #
b1 &
#6000
0s
0S
0<
b0 #
b0 &
#7000
b100 2"
b100 r
b100 M
1s
1S
1<
b1 #
b1 &
#8000
0s
0S
0<
b0 #
b0 &
#9000
b101 2"
b101 r
b101 M
1s
1S
1<
b1 #
b1 &
#10000
b1 /"
b0 *"
b0 &"
b0 %"
b0 e
b1 o
b0 j
b1 J
b0 E
b0 @
b0 f
0+"
b0 ."
b0 )"
01"
0w
b0 x
b0 0"
b0 -"
b0 ,"
b0 .
b0 O
b0 P
b0 {
b0 !"
b0 ~
b0 #"
b0 |
b0 $"
0)
b0 Y
b0 [
b0 _
b0 d
0*
b0 /
b0 \
b0 ]
0k
b0 n
b0 i
0q
0V
b0 Z
b0 a
b0 p
b0 m
b0 l
0F
b0 I
b0 D
0L
0+
b0 0
b0 K
b0 H
b0 G
b0 "
b0 1
04
05
06
b0 2
b0 >
b0 3
b0 U
b0 c
b0 7
b0 u
0!
0s
0S
0<
0t
0T
0?
b0 #
b0 &
b0 $
b0 '
#11000
1s
1S
1<
b1 #
b1 &
#12000
b0 }
0s
0S
0<
b0 #
b0 &
#13000
1s
1S
1<
b1 #
b1 &
#14000
0s
0S
0<
b0 #
b0 &
#15000
1s
1S
1<
b1 #
b1 &
#16000
0s
0S
0<
b0 #
b0 &
#17000
1s
1S
1<
b1 #
b1 &
#18000
0s
0S
0<
b0 #
b0 &
#19000
1s
1S
1<
b1 #
b1 &
#20000
0s
0S
0<
1t
1T
1?
b0 #
b0 &
b1 $
b1 '
#21000
11"
1q
1L
bx 7
bx u
1s
1S
1<
b1 #
b1 &
#22000
bx }
0s
0S
0<
b0 #
b0 &
#23000
1s
1S
1<
b1 #
b1 &
#24000
0s
0S
0<
b0 #
b0 &
#25000
1s
1S
1<
b1 #
b1 &
#26000
0s
0S
0<
b0 #
b0 &
#27000
1s
1S
1<
b1 #
b1 &
#28000
0s
0S
0<
b0 #
b0 &
#29000
1s
1S
1<
b1 #
b1 &
#30000
0s
0S
0<
b0 #
b0 &
b0 %
b0 (
#31000
b0 7
b0 u
1s
1S
1<
b1 #
b1 &
#32000
b0 }
0s
0S
0<
b0 #
b0 &
#33000
1s
1S
1<
b1 #
b1 &
#34000
0s
0S
0<
b0 #
b0 &
#35000
1s
1S
1<
b1 #
b1 &
#36000
0s
0S
0<
b0 #
b0 &
#37000
1s
1S
1<
b1 #
b1 &
#38000
0s
0S
0<
b0 #
b0 &
#39000
1s
1S
1<
b1 #
b1 &
#40000
0s
0S
0<
b0 #
b0 &
#41000
1s
1S
1<
b1 #
b1 &
#42000
0s
0S
0<
b0 #
b0 &
#43000
1s
1S
1<
b1 #
b1 &
#44000
0s
0S
0<
b0 #
b0 &
#45000
1s
1S
1<
b1 #
b1 &
#46000
0s
0S
0<
b0 #
b0 &
#47000
1s
1S
1<
b1 #
b1 &
#48000
0s
0S
0<
b0 #
b0 &
#49000
1s
1S
1<
b1 #
b1 &
#50000
0s
0S
0<
b0 #
b0 &
#51000
1s
1S
1<
b1 #
b1 &
#52000
0s
0S
0<
b0 #
b0 &
#53000
1s
1S
1<
b1 #
b1 &
#54000
0s
0S
0<
b0 #
b0 &
#55000
1s
1S
1<
b1 #
b1 &
#56000
0s
0S
0<
b0 #
b0 &
#57000
1s
1S
1<
b1 #
b1 &
#58000
0s
0S
0<
b0 #
b0 &
#59000
1s
1S
1<
b1 #
b1 &
#60000
0s
0S
0<
b0 #
b0 &
#61000
1s
1S
1<
b1 #
b1 &
#62000
0s
0S
0<
b0 #
b0 &
#63000
1s
1S
1<
b1 #
b1 &
#64000
0s
0S
0<
b0 #
b0 &
#65000
1s
1S
1<
b1 #
b1 &
#66000
0s
0S
0<
b0 #
b0 &
#67000
1s
1S
1<
b1 #
b1 &
#68000
0s
0S
0<
b0 #
b0 &
#69000
1s
1S
1<
b1 #
b1 &
#70000
0s
0S
0<
b0 #
b0 &
#71000
1s
1S
1<
b1 #
b1 &
#72000
0s
0S
0<
b0 #
b0 &
#73000
1s
1S
1<
b1 #
b1 &
#74000
0s
0S
0<
b0 #
b0 &
#75000
1s
1S
1<
b1 #
b1 &
#76000
0s
0S
0<
b0 #
b0 &
#77000
1s
1S
1<
b1 #
b1 &
#78000
0s
0S
0<
b0 #
b0 &
#79000
1s
1S
1<
b1 #
b1 &
#80000
0s
0S
0<
b0 #
b0 &
#81000
1s
1S
1<
b1 #
b1 &
#82000
0s
0S
0<
b0 #
b0 &
#83000
1s
1S
1<
b1 #
b1 &
#84000
0s
0S
0<
b0 #
b0 &
#85000
1s
1S
1<
b1 #
b1 &
#86000
0s
0S
0<
b0 #
b0 &
#87000
1s
1S
1<
b1 #
b1 &
#88000
0s
0S
0<
b0 #
b0 &
#89000
1s
1S
1<
b1 #
b1 &
#90000
0s
0S
0<
b0 #
b0 &
#91000
1s
1S
1<
b1 #
b1 &
#92000
0s
0S
0<
b0 #
b0 &
#93000
1s
1S
1<
b1 #
b1 &
#94000
0s
0S
0<
b0 #
b0 &
#95000
1s
1S
1<
b1 #
b1 &
#96000
0s
0S
0<
b0 #
b0 &
#97000
1s
1S
1<
b1 #
b1 &
#98000
0s
0S
0<
b0 #
b0 &
#99000
1s
1S
1<
b1 #
b1 &
#100000
0s
0S
0<
b0 #
b0 &
#101000
1s
1S
1<
b1 #
b1 &
#102000
0s
0S
0<
b0 #
b0 &
#103000
1s
1S
1<
b1 #
b1 &
#104000
0s
0S
0<
b0 #
b0 &
#105000
1s
1S
1<
b1 #
b1 &
#106000
0s
0S
0<
b0 #
b0 &
#107000
1s
1S
1<
b1 #
b1 &
#108000
0s
0S
0<
b0 #
b0 &
#109000
1s
1S
1<
b1 #
b1 &
#110000
0s
0S
0<
b0 #
b0 &
#111000
1s
1S
1<
b1 #
b1 &
#112000
0s
0S
0<
b0 #
b0 &
#113000
1s
1S
1<
b1 #
b1 &
#114000
0s
0S
0<
b0 #
b0 &
#115000
1s
1S
1<
b1 #
b1 &
#116000
0s
0S
0<
b0 #
b0 &
#117000
1s
1S
1<
b1 #
b1 &
#118000
0s
0S
0<
b0 #
b0 &
#119000
1s
1S
1<
b1 #
b1 &
#120000
0s
0S
0<
b0 #
b0 &
#121000
1s
1S
1<
b1 #
b1 &
#122000
0s
0S
0<
b0 #
b0 &
#123000
1s
1S
1<
b1 #
b1 &
#124000
0s
0S
0<
b0 #
b0 &
#125000
1s
1S
1<
b1 #
b1 &
#126000
0s
0S
0<
b0 #
b0 &
#127000
1s
1S
1<
b1 #
b1 &
#128000
0s
0S
0<
b0 #
b0 &
#129000
1s
1S
1<
b1 #
b1 &
#130000
0s
0S
0<
b0 #
b0 &
#131000
1s
1S
1<
b1 #
b1 &
#132000
0s
0S
0<
b0 #
b0 &
#133000
1s
1S
1<
b1 #
b1 &
#134000
0s
0S
0<
b0 #
b0 &
#135000
1s
1S
1<
b1 #
b1 &
#136000
0s
0S
0<
b0 #
b0 &
#137000
1s
1S
1<
b1 #
b1 &
#138000
0s
0S
0<
b0 #
b0 &
#139000
1s
1S
1<
b1 #
b1 &
#140000
0s
0S
0<
b0 #
b0 &
#141000
1s
1S
1<
b1 #
b1 &
#142000
0s
0S
0<
b0 #
b0 &
#143000
1s
1S
1<
b1 #
b1 &
#144000
0s
0S
0<
b0 #
b0 &
#145000
1s
1S
1<
b1 #
b1 &
#146000
0s
0S
0<
b0 #
b0 &
#147000
1s
1S
1<
b1 #
b1 &
#148000
0s
0S
0<
b0 #
b0 &
#149000
1s
1S
1<
b1 #
b1 &
#150000
0s
0S
0<
b0 #
b0 &
#151000
1s
1S
1<
b1 #
b1 &
#152000
0s
0S
0<
b0 #
b0 &
#153000
1s
1S
1<
b1 #
b1 &
#154000
0s
0S
0<
b0 #
b0 &
#155000
1s
1S
1<
b1 #
b1 &
#156000
0s
0S
0<
b0 #
b0 &
#157000
1s
1S
1<
b1 #
b1 &
#158000
0s
0S
0<
b0 #
b0 &
#159000
1s
1S
1<
b1 #
b1 &
#160000
0s
0S
0<
b0 #
b0 &
#161000
1s
1S
1<
b1 #
b1 &
#162000
0s
0S
0<
b0 #
b0 &
#163000
1s
1S
1<
b1 #
b1 &
#164000
0s
0S
0<
b0 #
b0 &
#165000
1s
1S
1<
b1 #
b1 &
#166000
0s
0S
0<
b0 #
b0 &
#167000
1s
1S
1<
b1 #
b1 &
#168000
0s
0S
0<
b0 #
b0 &
#169000
1s
1S
1<
b1 #
b1 &
#170000
0s
0S
0<
b0 #
b0 &
#171000
1s
1S
1<
b1 #
b1 &
#172000
0s
0S
0<
b0 #
b0 &
#173000
1s
1S
1<
b1 #
b1 &
#174000
0s
0S
0<
b0 #
b0 &
#175000
1s
1S
1<
b1 #
b1 &
#176000
0s
0S
0<
b0 #
b0 &
#177000
1s
1S
1<
b1 #
b1 &
#178000
0s
0S
0<
b0 #
b0 &
#179000
1s
1S
1<
b1 #
b1 &
#180000
0s
0S
0<
b0 #
b0 &
#181000
1s
1S
1<
b1 #
b1 &
#182000
0s
0S
0<
b0 #
b0 &
#183000
1s
1S
1<
b1 #
b1 &
#184000
0s
0S
0<
b0 #
b0 &
#185000
1s
1S
1<
b1 #
b1 &
#186000
0s
0S
0<
b0 #
b0 &
#187000
1s
1S
1<
b1 #
b1 &
#188000
0s
0S
0<
b0 #
b0 &
#189000
1s
1S
1<
b1 #
b1 &
#190000
0s
0S
0<
b0 #
b0 &
#191000
1s
1S
1<
b1 #
b1 &
#192000
0s
0S
0<
b0 #
b0 &
#193000
1s
1S
1<
b1 #
b1 &
#194000
0s
0S
0<
b0 #
b0 &
#195000
1s
1S
1<
b1 #
b1 &
#196000
0s
0S
0<
b0 #
b0 &
#197000
1s
1S
1<
b1 #
b1 &
#198000
0s
0S
0<
b0 #
b0 &
#199000
1s
1S
1<
b1 #
b1 &
#200000
0s
0S
0<
b0 #
b0 &
#201000
1s
1S
1<
b1 #
b1 &
#202000
0s
0S
0<
b0 #
b0 &
#203000
1s
1S
1<
b1 #
b1 &
#204000
0s
0S
0<
b0 #
b0 &
#205000
1s
1S
1<
b1 #
b1 &
#206000
0s
0S
0<
b0 #
b0 &
#207000
1s
1S
1<
b1 #
b1 &
#208000
0s
0S
0<
b0 #
b0 &
#209000
1s
1S
1<
b1 #
b1 &
#210000
0s
0S
0<
b0 #
b0 &
#211000
1s
1S
1<
b1 #
b1 &
#212000
0s
0S
0<
b0 #
b0 &
#213000
1s
1S
1<
b1 #
b1 &
#214000
0s
0S
0<
b0 #
b0 &
#215000
1s
1S
1<
b1 #
b1 &
#216000
0s
0S
0<
b0 #
b0 &
#217000
1s
1S
1<
b1 #
b1 &
#218000
0s
0S
0<
b0 #
b0 &
#219000
1s
1S
1<
b1 #
b1 &
#220000
0s
0S
0<
b0 #
b0 &
#221000
1s
1S
1<
b1 #
b1 &
