user/src/arm/push_pwm.v
//pwm波输出器
//输入：时钟clk 50MHz，高电平持续时间duty（50_000代表1ms）（上限1_000_000即20ms）
//输出：周期20ms的pwm波pwm_wave
//功能：根据给定的duty输出pwm波
module push_pwm(
        input clk,//输入时钟50MHz
        input rst_n,//复位信号，低电平有效
        input [19:0] duty,
        output reg pwm_wave
    );

    reg [19:0] count=0;

    always @(posedge clk or negedge rst_n) begin
        if(!rst_n) begin
            count<=0;
            pwm_wave<=0;
        end
        else begin
            //if(count==19)//仅用于仿真
            if(count==999_999)//20ms
            begin
                count<=0;
            end
            else begin
                count<=count+1;
            end
            if(count<duty)//duty输入50_000时，高电平1ms
            begin
                pwm_wave<=1'b1;
            end
            else begin
                pwm_wave<=1'b0;
            end
        end
    end
endmodule

user/sim/arm/push_pwm_tb.v
`timescale  1ns / 1ps

module push_pwm_tb;

// Parameters

// Ports
reg clk = 0;
reg rst_n = 0;
reg [19:0] duty;
wire pwm_wave;

push_pwm 
push_pwm_dut (
  .clk (clk ),
  .rst_n (rst_n ),
  .duty (duty ),
  .pwm_wave  ( pwm_wave)
);

initial begin
        $dumpfile("push_pwm_tb.vcd");
        $dumpvars(0, push_pwm_tb);
        rst_n=0;
        #10 rst_n=1;
        duty=10;
        #1000
        duty=5; 
        #1000
        $finish;
end

always
  #5  clk = ! clk ;

endmodule

push_pwm_tb.vcd
$date
	Sat Jul 08 14:41:17 2023
$end
$version
	Icarus Verilog
$end
$timescale
	1ps
$end
$scope module push_pwm_tb $end
$var wire 1 ! pwm_wave $end
$var reg 1 " clk $end
$var reg 20 # duty [19:0] $end
$var reg 1 $ rst_n $end
$scope module push_pwm_dut $end
$var wire 1 " clk $end
$var wire 20 % duty [19:0] $end
$var wire 1 $ rst_n $end
$var reg 20 & count [19:0] $end
$var reg 1 ! pwm_wave $end
$upscope $end
$upscope $end
$enddefinitions $end
$comment Show the parameter values. $end
$dumpall
$end
#0
$dumpvars
b0 &
bx %
0$
bx #
0"
x!
$end
#5000
0!
1"
#10000
0"
b1010 #
b1010 %
1$
#15000
1!
b1 &
1"
#20000
0"
#25000
b10 &
1"
#30000
0"
#35000
b11 &
1"
#40000
0"
#45000
b100 &
1"
#50000
0"
#55000
b101 &
1"
#60000
0"
#65000
b110 &
1"
#70000
0"
#75000
b111 &
1"
#80000
0"
#85000
b1000 &
1"
#90000
0"
#95000
b1001 &
1"
#100000
0"
#105000
b1010 &
1"
#110000
0"
#115000
0!
b1011 &
1"
#120000
0"
#125000
b1100 &
1"
#130000
0"
#135000
b1101 &
1"
#140000
0"
#145000
b1110 &
1"
#150000
0"
#155000
b1111 &
1"
#160000
0"
#165000
b10000 &
1"
#170000
0"
#175000
b10001 &
1"
#180000
0"
#185000
b10010 &
1"
#190000
0"
#195000
b10011 &
1"
#200000
0"
#205000
b0 &
1"
#210000
0"
#215000
1!
b1 &
1"
#220000
0"
#225000
b10 &
1"
#230000
0"
#235000
b11 &
1"
#240000
0"
#245000
b100 &
1"
#250000
0"
#255000
b101 &
1"
#260000
0"
#265000
b110 &
1"
#270000
0"
#275000
b111 &
1"
#280000
0"
#285000
b1000 &
1"
#290000
0"
#295000
b1001 &
1"
#300000
0"
#305000
b1010 &
1"
#310000
0"
#315000
0!
b1011 &
1"
#320000
0"
#325000
b1100 &
1"
#330000
0"
#335000
b1101 &
1"
#340000
0"
#345000
b1110 &
1"
#350000
0"
#355000
b1111 &
1"
#360000
0"
#365000
b10000 &
1"
#370000
0"
#375000
b10001 &
1"
#380000
0"
#385000
b10010 &
1"
#390000
0"
#395000
b10011 &
1"
#400000
0"
#405000
b0 &
1"
#410000
0"
#415000
1!
b1 &
1"
#420000
0"
#425000
b10 &
1"
#430000
0"
#435000
b11 &
1"
#440000
0"
#445000
b100 &
1"
#450000
0"
#455000
b101 &
1"
#460000
0"
#465000
b110 &
1"
#470000
0"
#475000
b111 &
1"
#480000
0"
#485000
b1000 &
1"
#490000
0"
#495000
b1001 &
1"
#500000
0"
#505000
b1010 &
1"
#510000
0"
#515000
0!
b1011 &
1"
#520000
0"
#525000
b1100 &
1"
#530000
0"
#535000
b1101 &
1"
#540000
0"
#545000
b1110 &
1"
#550000
0"
#555000
b1111 &
1"
#560000
0"
#565000
b10000 &
1"
#570000
0"
#575000
b10001 &
1"
#580000
0"
#585000
b10010 &
1"
#590000
0"
#595000
b10011 &
1"
#600000
0"
#605000
b0 &
1"
#610000
0"
#615000
1!
b1 &
1"
#620000
0"
#625000
b10 &
1"
#630000
0"
#635000
b11 &
1"
#640000
0"
#645000
b100 &
1"
#650000
0"
#655000
b101 &
1"
#660000
0"
#665000
b110 &
1"
#670000
0"
#675000
b111 &
1"
#680000
0"
#685000
b1000 &
1"
#690000
0"
#695000
b1001 &
1"
#700000
0"
#705000
b1010 &
1"
#710000
0"
#715000
0!
b1011 &
1"
#720000
0"
#725000
b1100 &
1"
#730000
0"
#735000
b1101 &
1"
#740000
0"
#745000
b1110 &
1"
#750000
0"
#755000
b1111 &
1"
#760000
0"
#765000
b10000 &
1"
#770000
0"
#775000
b10001 &
1"
#780000
0"
#785000
b10010 &
1"
#790000
0"
#795000
b10011 &
1"
#800000
0"
#805000
b0 &
1"
#810000
0"
#815000
1!
b1 &
1"
#820000
0"
#825000
b10 &
1"
#830000
0"
#835000
b11 &
1"
#840000
0"
#845000
b100 &
1"
#850000
0"
#855000
b101 &
1"
#860000
0"
#865000
b110 &
1"
#870000
0"
#875000
b111 &
1"
#880000
0"
#885000
b1000 &
1"
#890000
0"
#895000
b1001 &
1"
#900000
0"
#905000
b1010 &
1"
#910000
0"
#915000
0!
b1011 &
1"
#920000
0"
#925000
b1100 &
1"
#930000
0"
#935000
b1101 &
1"
#940000
0"
#945000
b1110 &
1"
#950000
0"
#955000
b1111 &
1"
#960000
0"
#965000
b10000 &
1"
#970000
0"
#975000
b10001 &
1"
#980000
0"
#985000
b10010 &
1"
#990000
0"
#995000
b10011 &
1"
#1000000
0"
#1005000
b0 &
1"
#1010000
0"
b101 #
b101 %
#1015000
1!
b1 &
1"
#1020000
0"
#1025000
b10 &
1"
#1030000
0"
#1035000
b11 &
1"
#1040000
0"
#1045000
b100 &
1"
#1050000
0"
#1055000
b101 &
1"
#1060000
0"
#1065000
0!
b110 &
1"
#1070000
0"
#1075000
b111 &
1"
#1080000
0"
#1085000
b1000 &
1"
#1090000
0"
#1095000
b1001 &
1"
#1100000
0"
#1105000
b1010 &
1"
#1110000
0"
#1115000
b1011 &
1"
#1120000
0"
#1125000
b1100 &
1"
#1130000
0"
#1135000
b1101 &
1"
#1140000
0"
#1145000
b1110 &
1"
#1150000
0"
#1155000
b1111 &
1"
#1160000
0"
#1165000
b10000 &
1"
#1170000
0"
#1175000
b10001 &
1"
#1180000
0"
#1185000
b10010 &
1"
#1190000
0"
#1195000
b10011 &
1"
#1200000
0"
#1205000
b0 &
1"
#1210000
0"
#1215000
1!
b1 &
1"
#1220000
0"
#1225000
b10 &
1"
#1230000
0"
#1235000
b11 &
1"
#1240000
0"
#1245000
b100 &
1"
#1250000
0"
#1255000
b101 &
1"
#1260000
0"
#1265000
0!
b110 &
1"
#1270000
0"
#1275000
b111 &
1"
#1280000
0"
#1285000
b1000 &
1"
#1290000
0"
#1295000
b1001 &
1"
#1300000
0"
#1305000
b1010 &
1"
#1310000
0"
#1315000
b1011 &
1"
#1320000
0"
#1325000
b1100 &
1"
#1330000
0"
#1335000
b1101 &
1"
#1340000
0"
#1345000
b1110 &
1"
#1350000
0"
#1355000
b1111 &
1"
#1360000
0"
#1365000
b10000 &
1"
#1370000
0"
#1375000
b10001 &
1"
#1380000
0"
#1385000
b10010 &
1"
#1390000
0"
#1395000
b10011 &
1"
#1400000
0"
#1405000
b0 &
1"
#1410000
0"
#1415000
1!
b1 &
1"
#1420000
0"
#1425000
b10 &
1"
#1430000
0"
#1435000
b11 &
1"
#1440000
0"
#1445000
b100 &
1"
#1450000
0"
#1455000
b101 &
1"
#1460000
0"
#1465000
0!
b110 &
1"
#1470000
0"
#1475000
b111 &
1"
#1480000
0"
#1485000
b1000 &
1"
#1490000
0"
#1495000
b1001 &
1"
#1500000
0"
#1505000
b1010 &
1"
#1510000
0"
#1515000
b1011 &
1"
#1520000
0"
#1525000
b1100 &
1"
#1530000
0"
#1535000
b1101 &
1"
#1540000
0"
#1545000
b1110 &
1"
#1550000
0"
#1555000
b1111 &
1"
#1560000
0"
#1565000
b10000 &
1"
#1570000
0"
#1575000
b10001 &
1"
#1580000
0"
#1585000
b10010 &
1"
#1590000
0"
#1595000
b10011 &
1"
#1600000
0"
#1605000
b0 &
1"
#1610000
0"
#1615000
1!
b1 &
1"
#1620000
0"
#1625000
b10 &
1"
#1630000
0"
#1635000
b11 &
1"
#1640000
0"
#1645000
b100 &
1"
#1650000
0"
#1655000
b101 &
1"
#1660000
0"
#1665000
0!
b110 &
1"
#1670000
0"
#1675000
b111 &
1"
#1680000
0"
#1685000
b1000 &
1"
#1690000
0"
#1695000
b1001 &
1"
#1700000
0"
#1705000
b1010 &
1"
#1710000
0"
#1715000
b1011 &
1"
#1720000
0"
#1725000
b1100 &
1"
#1730000
0"
#1735000
b1101 &
1"
#1740000
0"
#1745000
b1110 &
1"
#1750000
0"
#1755000
b1111 &
1"
#1760000
0"
#1765000
b10000 &
1"
#1770000
0"
#1775000
b10001 &
1"
#1780000
0"
#1785000
b10010 &
1"
#1790000
0"
#1795000
b10011 &
1"
#1800000
0"
#1805000
b0 &
1"
#1810000
0"
#1815000
1!
b1 &
1"
#1820000
0"
#1825000
b10 &
1"
#1830000
0"
#1835000
b11 &
1"
#1840000
0"
#1845000
b100 &
1"
#1850000
0"
#1855000
b101 &
1"
#1860000
0"
#1865000
0!
b110 &
1"
#1870000
0"
#1875000
b111 &
1"
#1880000
0"
#1885000
b1000 &
1"
#1890000
0"
#1895000
b1001 &
1"
#1900000
0"
#1905000
b1010 &
1"
#1910000
0"
#1915000
b1011 &
1"
#1920000
0"
#1925000
b1100 &
1"
#1930000
0"
#1935000
b1101 &
1"
#1940000
0"
#1945000
b1110 &
1"
#1950000
0"
#1955000
b1111 &
1"
#1960000
0"
#1965000
b10000 &
1"
#1970000
0"
#1975000
b10001 &
1"
#1980000
0"
#1985000
b10010 &
1"
#1990000
0"
#1995000
b10011 &
1"
#2000000
0"
#2005000
b0 &
1"
