user/src/basic/qdiv.v
`ifndef QDIV_V
`define QDIV_V

module qdiv(
    input clk,
    input rst_n,
    input [31:0] dividend,
    input [31:0] divisor,
    output reg [31:0] quotient,
    output reg valid,//运算完成信号
    output reg warn,//除数为0警告
    output reg busy//运算中信号
    );

    parameter WIDTH = 31;
    parameter  FBITS = 16;

    wire [WIDTH-1:0] dividend_unsigned;
    wire [WIDTH-1:0] divisor_unsigned;

    integer i=0;

    reg [WIDTH-1:0] dividend_reg;//被除数寄存器(不带符号)
    reg [WIDTH-1:0] divisor_reg;//除数寄存器(不带符号)
    reg [WIDTH:0] acc;//单次被除数
    reg [WIDTH-1:0] quo;//实际使用中移位的被除数和商(复用)

    reg [WIDTH:0] acc_next;//单次被除数下一个
    reg [WIDTH-1:0] quo_next;//实际使用中移位的被除数下一个

    assign dividend_unsigned=dividend[WIDTH-1:0];
    assign divisor_unsigned=divisor[WIDTH-1:0];

    always @(*) 
    begin
      if (acc >= {1'b0, divisor_reg}) 
      begin
        acc_next = acc - divisor_reg;
        {acc_next, quo_next} = {acc_next[WIDTH-1:0], quo, 1'b1};
      end 
      else 
      begin
        {acc_next, quo_next} = {acc, quo} << 1;
      end
    end

    always @(negedge clk or negedge rst_n) 
    begin
        if(!rst_n)
        begin
            dividend_reg <= 0;
            divisor_reg <= 0;
            quotient <= 0;
            valid <= 0;
            warn <= 0;
            acc <= 0;
            quo <= 0;
            busy <= 0;

            acc_next <= 0;
            quo_next <= 0;
        end
        else if(divisor==0)
        begin
            warn <= 1;
            valid <= 0;
            quotient <= 0;
            busy <= 0;
        end
        else
        begin
            dividend_reg <= dividend_unsigned;
            divisor_reg <= divisor_unsigned;
            if(dividend_unsigned!=dividend_reg||divisor_unsigned!=divisor_reg)//输入变化，重新计算
            begin
                i <= 0;
                valid <= 0;
                {acc, quo} <= {{WIDTH{1'b0}}, dividend_unsigned, 1'b0};
                busy <= 1'b1;
            end
            else
            begin
                if(i==WIDTH+FBITS-1)
                begin
                    valid<=1;
                    busy <= 1'b0;
                    if(dividend[WIDTH]==divisor[WIDTH])
                      quotient<={1'b0,quo_next[WIDTH-1:0]};
                    else
                      quotient<={1'b1,quo_next[WIDTH-1:0]};
                end
                else
                begin
                    i<=i+1;
                    {acc, quo} <= {acc_next, quo_next};
                end
            end
        end
    end
endmodule
`endif

user/sim/basic/qdiv_tb.v
`timescale 1ns/1ps
module qdiv_tb;

  // Parameters
  localparam  WIDTH = 31;
  localparam  FBITS = 16;

  // Ports
  reg clk = 0;
  reg rst_n = 0;
  reg [31:0] dividend;
  reg [31:0] divisor;
  wire [31:0] quotient;
  wire valid;
  wire warn;
  wire busy;

  qdiv 
  #(
    .WIDTH(WIDTH ),
    .FBITS (
        FBITS )
  )
  qdiv_dut (
    .clk (clk ),
    .rst_n (rst_n ),
    .dividend (dividend ),
    .divisor (divisor ),
    .quotient (quotient ),
    .valid (valid ),
    .warn (warn ),
    .busy  ( busy)
  );

  initial begin
    begin
        $dumpfile("qdiv_tb.vcd");
        $dumpvars(0, qdiv_tb);
        rst_n=0;
        #10
        rst_n=1;
        dividend=32'h00080000;
        divisor=32'h00020000;
        #1000
        dividend=32'h00070000;
        divisor=32'h00030000;
        #1000
        dividend=32'h80060000;
        divisor=32'h00030000;
        #1000
        dividend=32'h80060000;
        divisor=32'h80020000;
        #1000
        $finish;
    end
  end

  always
    #1  clk = ! clk ;

endmodule

qdiv_tb.vcd
$date
	Mon Jul 03 15:14:37 2023
$end
$version
	Icarus Verilog
$end
$timescale
	1ps
$end
$scope module qdiv_tb $end
$var wire 1 ! warn $end
$var wire 1 " valid $end
$var wire 32 # quotient [31:0] $end
$var wire 1 $ busy $end
$var parameter 32 % FBITS $end
$var parameter 32 & WIDTH $end
$var reg 1 ' clk $end
$var reg 32 ( dividend [31:0] $end
$var reg 32 ) divisor [31:0] $end
$var reg 1 * rst_n $end
$scope module qdiv_dut $end
$var wire 1 ' clk $end
$var wire 32 + dividend [31:0] $end
$var wire 32 , divisor [31:0] $end
$var wire 1 * rst_n $end
$var wire 31 - divisor_unsigned [30:0] $end
$var wire 31 . dividend_unsigned [30:0] $end
$var parameter 32 / FBITS $end
$var parameter 32 0 WIDTH $end
$var reg 32 1 acc [31:0] $end
$var reg 32 2 acc_next [31:0] $end
$var reg 1 $ busy $end
$var reg 31 3 dividend_reg [30:0] $end
$var reg 31 4 divisor_reg [30:0] $end
$var reg 31 5 quo [30:0] $end
$var reg 31 6 quo_next [30:0] $end
$var reg 32 7 quotient [31:0] $end
$var reg 1 " valid $end
$var reg 1 ! warn $end
$var integer 32 8 i [31:0] $end
$upscope $end
$upscope $end
$enddefinitions $end
$comment Show the parameter values. $end
$dumpall
b11111 0
b10000 /
b11111 &
b10000 %
$end
#0
$dumpvars
b0 8
bx 7
bx 6
bx 5
bx 4
bx 3
bx 2
bx 1
bx .
bx -
bx ,
bx +
0*
bx )
bx (
0'
x$
bx #
x"
x!
$end
#1000
1'
#2000
b1 6
b0 2
0$
b0 5
b0 1
0!
0"
b0 #
b0 7
b0 4
b0 3
0'
#3000
1'
#4000
b0 6
0'
#5000
1'
#6000
0'
#7000
1'
#8000
0'
#9000
1'
#10000
b1000000000000000000000 6
1$
b100000000000000000000 5
b100000000000000000 4
b10000000000000000000 3
b100000000000000000 -
b10000000000000000000 .
0'
b100000000000000000 )
b100000000000000000 ,
b10000000000000000000 (
b10000000000000000000 +
1*
#11000
1'
#12000
b10000000000000000000000 6
b1000000000000000000000 5
b1 8
0'
#13000
1'
#14000
b100000000000000000000000 6
b10000000000000000000000 5
b10 8
0'
#15000
1'
#16000
b1000000000000000000000000 6
b100000000000000000000000 5
b11 8
0'
#17000
1'
#18000
b10000000000000000000000000 6
b1000000000000000000000000 5
b100 8
0'
#19000
1'
#20000
b100000000000000000000000000 6
b10000000000000000000000000 5
b101 8
0'
#21000
1'
#22000
b1000000000000000000000000000 6
b100000000000000000000000000 5
b110 8
0'
#23000
1'
#24000
b10000000000000000000000000000 6
b1000000000000000000000000000 5
b111 8
0'
#25000
1'
#26000
b100000000000000000000000000000 6
b10000000000000000000000000000 5
b1000 8
0'
#27000
1'
#28000
b1000000000000000000000000000000 6
b100000000000000000000000000000 5
b1001 8
0'
#29000
1'
#30000
b1 2
b0 6
b1000000000000000000000000000000 5
b1010 8
0'
#31000
1'
#32000
b10 2
b1 1
b0 5
b1011 8
0'
#33000
1'
#34000
b100 2
b10 1
b1100 8
0'
#35000
1'
#36000
b1000 2
b100 1
b1101 8
0'
#37000
1'
#38000
b10000 2
b1000 1
b1110 8
0'
#39000
1'
#40000
b100000 2
b10000 1
b1111 8
0'
#41000
1'
#42000
b1000000 2
b100000 1
b10000 8
0'
#43000
1'
#44000
b10000000 2
b1000000 1
b10001 8
0'
#45000
1'
#46000
b100000000 2
b10000000 1
b10010 8
0'
#47000
1'
#48000
b1000000000 2
b100000000 1
b10011 8
0'
#49000
1'
#50000
b10000000000 2
b1000000000 1
b10100 8
0'
#51000
1'
#52000
b100000000000 2
b10000000000 1
b10101 8
0'
#53000
1'
#54000
b1000000000000 2
b100000000000 1
b10110 8
0'
#55000
1'
#56000
b10000000000000 2
b1000000000000 1
b10111 8
0'
#57000
1'
#58000
b100000000000000 2
b10000000000000 1
b11000 8
0'
#59000
1'
#60000
b1000000000000000 2
b100000000000000 1
b11001 8
0'
#61000
1'
#62000
b10000000000000000 2
b1000000000000000 1
b11010 8
0'
#63000
1'
#64000
b100000000000000000 2
b10000000000000000 1
b11011 8
0'
#65000
1'
#66000
b1 6
b0 2
b100000000000000000 1
b11100 8
0'
#67000
1'
#68000
b10 6
b0 1
b1 5
b11101 8
0'
#69000
1'
#70000
b100 6
b10 5
b11110 8
0'
#71000
1'
#72000
b1000 6
b100 5
b11111 8
0'
#73000
1'
#74000
b10000 6
b1000 5
b100000 8
0'
#75000
1'
#76000
b100000 6
b10000 5
b100001 8
0'
#77000
1'
#78000
b1000000 6
b100000 5
b100010 8
0'
#79000
1'
#80000
b10000000 6
b1000000 5
b100011 8
0'
#81000
1'
#82000
b100000000 6
b10000000 5
b100100 8
0'
#83000
1'
#84000
b1000000000 6
b100000000 5
b100101 8
0'
#85000
1'
#86000
b10000000000 6
b1000000000 5
b100110 8
0'
#87000
1'
#88000
b100000000000 6
b10000000000 5
b100111 8
0'
#89000
1'
#90000
b1000000000000 6
b100000000000 5
b101000 8
0'
#91000
1'
#92000
b10000000000000 6
b1000000000000 5
b101001 8
0'
#93000
1'
#94000
b100000000000000 6
b10000000000000 5
b101010 8
0'
#95000
1'
#96000
b1000000000000000 6
b100000000000000 5
b101011 8
0'
#97000
1'
#98000
b10000000000000000 6
b1000000000000000 5
b101100 8
0'
#99000
1'
#100000
b100000000000000000 6
b10000000000000000 5
b101101 8
0'
#101000
1'
#102000
b1000000000000000000 6
b100000000000000000 5
b101110 8
0'
#103000
1'
#104000
b1000000000000000000 #
b1000000000000000000 7
0$
1"
0'
