user/src/basic/qmulti.v
`ifndef QMULTI_V
`define QMULTI_V
module qmulti(
    input [31:0] multi1,
    input [31:0] multi2,
    output [31:0] result
);

reg [63:0] tmp=0;
reg [31:0] result_out=0;

assign result=result_out;

always @(*) 
begin
    tmp=multi1[30:0]*multi2[30:0];
    if(multi1[31]==multi2[31])
    begin
        result_out={1'b0,tmp[46:16]};
    end
    else
    begin
        result_out={1'b1,tmp[46:16]};
    end
end

endmodule
`endif

user/src/basic/qadd.v
//小数加法器，32位数据，31位为符号位，30-16位为整数位，15-0位为小数位
//输入：加数32位的add1,add2
//输出：和数32位的sum
`ifndef QADD_V
`define QADD_V
module qadd
(
    input [31:0] add1,
    input [31:0] add2,
    output [31:0] sum
);
    reg[31:0] res=0;//暂存加的结果

    assign sum = res;

    always @(*) 
    begin
        if(add1[31]==add2[31])//同号相加
        begin
            res[31] = add1[31];
            if(add1[30:0]+add2[30:0]>=2**31)//判断是否溢出
            begin
                res[30:0] = add1[30:0]+add2[30:0]-2**31;
            end
            else
            begin
                res[30:0] = add1[30:0]+add2[30:0];
            end
        end
        else//异号则数字位相减
        begin
            if(add1[30:0]>add2[30:0])
            begin
                res[31] = add1[31];
                res[30:0] = add1[30:0]-add2[30:0];
            end
            else if(add1[30:0]<add2[30:0])
            begin
                res[31] = add2[31];
                res[30:0] = add2[30:0]-add1[30:0];
            end
            else
            begin
                res[31] = 1'b0;
                res[30:0] = 0;
            end
        end
    end
endmodule
`endif

user/src/basic/qdiv.v
`ifndef QDIV_V
`define QDIV_V

module qdiv(
    input clk,
    input rst_n,
    input [31:0] dividend,
    input [31:0] divisor,
    output reg [31:0] quotient,
    output reg valid,//运算完成信号
    output reg warn,//除数为0警告
    output reg busy//运算中信号
    );

    parameter WIDTH = 31;
    parameter  FBITS = 16;

  integer i=0;

    reg [WIDTH-1:0] dividend_reg;//被除数寄存器(不带符号)
    reg [WIDTH-1:0] divisor_reg;//除数寄存器(不带符号)
    reg [WIDTH:0] acc;//单次被除数
    reg [WIDTH-1:0] quo;//实际使用中移位的被除数和商(复用)

    reg [WIDTH:0] acc_next;//单次被除数下一个
    reg [WIDTH-1:0] quo_next;//实际使用中移位的被除数下一个

  always @(*) 
  begin
    if (acc >= {1'b0, divisor_reg}) 
    begin
      acc_next = acc - divisor_reg;
      {acc_next, quo_next} = {acc_next[WIDTH-1:0], quo, 1'b1};
    end 
    else 
    begin
      {acc_next, quo_next} = {acc, quo} << 1;
    end
  end

    always @(negedge clk or negedge rst_n) 
    begin
        if(!rst_n)
        begin
            dividend_reg <= 0;
            divisor_reg <= 0;
            quotient <= 0;
            valid <= 0;
            warn <= 0;
            acc <= 0;
            quo <= 0;
        end
        else if(divisor==0)
        begin
            warn <= 1;
            valid <= 0;
            quotient <= 0;
            busy <= 0;
        end
        else
        begin
            dividend_reg <= dividend;
            divisor_reg <= divisor;
            if(dividend!=dividend_reg||divisor!=divisor_reg)//输入变化，重新计算
            begin
                i <= 0;
                valid <= 0;
                {acc, quo} <= {{WIDTH{1'b0}}, dividend, 1'b0};
                busy <= 1'b1;
            end
            else
            begin
                if(i==WIDTH+FBITS-1)
                begin
                    valid<=1;
                    quotient<=quo_next[WIDTH-1:0];
                    busy <= 1'b0;
                end
                else
                begin
                    i<=i+1;
                    {acc, quo} <= {acc_next, quo_next};
                end
            end
        end
    end
endmodule
`endif

user/src/basic/sqrt.v
//`include "../qmulti/qmulti.v"
//`include "../qdiv/qdiv.v"
//`include "../qadd/qadd.v"
`ifndef SQRT_V
`define SQRT_V
module sqrt(
    input clk,
    input rst_n,
    output reg valid,

    input [31:0] sqrter,
    output reg [31:0] sqrted
);

    wire [31:0] iter;
    wire [31:0] two;
    wire [31:0] dived;
    wire [31:0] sum;
    wire [31:0] iter_next;
    wire valid_dived;

    reg [31:0] sqrter_reg;
    reg [31:0] iter_reg;

    integer i=0;
    
    assign iter = iter_reg;
    assign iter_next = sum>>1;

    qdiv 
    qdiv_dut1 (
        .clk (clk ),
        .rst_n (rst_n ),
        .valid(valid_dived),
        .busy(),
        .dividend (sqrter ),
        .divisor (iter ),
        .quotient (dived ),
        .warn  ( )
    );
    qadd
    qadd_dut (
        .add1 (dived ),
        .add2 (iter ),
        .sum (sum )
    );

    always @(negedge clk or negedge rst_n) 
    begin
        if(rst_n==0)
        begin
            sqrter_reg <= 0;
            sqrted <= 0;
            i <= 0;
            valid <= 0;
            iter_reg <= 0;
        end
        else
        begin
            sqrter_reg <= sqrter;
            if(sqrter_reg != sqrter)
            begin
                i <= 0;
                iter_reg <= sqrter;
                valid <= 0;
            end
            else if(i == 21)
            begin
                sqrted <= iter;
                valid <= 1;
            end
            else
            begin
                if(valid_dived)
                begin
                    iter_reg <= iter_next;
                    i <= i+1;
                end
            end
        end
    end

endmodule
`endif

user/sim/basic/sqrt_tb.v
`timescale 1ns / 1ps
module sqrt_tb;

// Parameters

// Ports
reg clk = 0;
reg rst_n = 0;
reg [31:0] sqrter;
wire [31:0] sqrted;

sqrt 
sqrt_dut (
  .clk (clk ),
  .rst_n (rst_n ),
  .sqrter (sqrter ),
  .sqrted  ( sqrted)
);

initial begin
  begin
      $dumpfile("sqrt_tb.vcd");
      $dumpvars(0, sqrt_tb);
      rst_n=0;
      #10
      rst_n=1;
      sqrter=32'h00040000;
      #10000
      sqrter=32'h00070000;
      #10000
      sqrter=32'h00100000;
      #10000
      $finish;
  end
end

always
  #1  clk = ! clk ;

endmodule

sqrt_tb.vcd
$date
	Mon Jul 03 14:57:35 2023
$end
$version
	Icarus Verilog
$end
$timescale
	1ps
$end
$scope module sqrt_tb $end
$var wire 32 ! sqrted [31:0] $end
$var reg 1 " clk $end
$var reg 1 # rst_n $end
$var reg 32 $ sqrter [31:0] $end
$scope module sqrt_dut $end
$var wire 1 " clk $end
$var wire 32 % iter [31:0] $end
$var wire 1 # rst_n $end
$var wire 32 & sqrter [31:0] $end
$var wire 1 ' valid_dived $end
$var wire 32 ( sum [31:0] $end
$var wire 32 ) iter_next [31:0] $end
$var wire 32 * dived [31:0] $end
$var reg 32 + iter_reg [31:0] $end
$var reg 32 , sqrted [31:0] $end
$var reg 32 - sqrter_reg [31:0] $end
$var reg 1 . valid $end
$var integer 32 / i [31:0] $end
$scope module qadd_dut $end
$var wire 32 0 add2 [31:0] $end
$var wire 32 1 sum [31:0] $end
$var wire 32 2 add1 [31:0] $end
$var reg 32 3 res [31:0] $end
$upscope $end
$scope module qdiv_dut1 $end
$var wire 1 " clk $end
$var wire 32 4 dividend [31:0] $end
$var wire 32 5 divisor [31:0] $end
$var wire 1 # rst_n $end
$var parameter 32 6 FBITS $end
$var parameter 32 7 WIDTH $end
$var reg 32 8 acc [31:0] $end
$var reg 32 9 acc_next [31:0] $end
$var reg 1 : busy $end
$var reg 31 ; dividend_reg [30:0] $end
$var reg 31 < divisor_reg [30:0] $end
$var reg 31 = quo [30:0] $end
$var reg 31 > quo_next [30:0] $end
$var reg 32 ? quotient [31:0] $end
$var reg 1 ' valid $end
$var reg 1 @ warn $end
$var integer 32 A i [31:0] $end
$upscope $end
$upscope $end
$upscope $end
$enddefinitions $end
$comment Show the parameter values. $end
$dumpall
b11111 7
b10000 6
$end
#0
$dumpvars
b0 A
x@
bx ?
bx >
bx =
bx <
bx ;
x:
bx 9
bx 8
bx 5
bx 4
b0 3
bx 2
b0 1
bx 0
b0 /
x.
bx -
bx ,
bx +
bx *
b0 )
b0 (
x'
bx &
bx %
bx $
0#
0"
bx !
$end
#1000
1"
#2000
b1 >
b0 9
0:
b0 =
b0 8
0@
0'
b0 *
b0 2
b0 ?
b0 <
b0 ;
b0 %
b0 0
b0 5
b0 +
0.
b0 !
b0 ,
b0 -
0"
#3000
1"
#4000
b0 >
0"
#5000
1"
#6000
0"
#7000
1"
#8000
0"
#9000
1"
#10000
b100000000000000000 )
b1000000000000000000 (
b1000000000000000000 1
b1000000000000000000 3
1@
b1000000000000000000 %
b1000000000000000000 0
b1000000000000000000 5
b1000000000000000000 +
b1000000000000000000 -
0"
b1000000000000000000 $
b1000000000000000000 &
b1000000000000000000 4
1#
#11000
1"
#12000
b100000000000000000000 >
1:
b10000000000000000000 =
b1000000000000000000 <
b1000000000000000000 ;
0"
#13000
1"
#14000
b1000000000000000000000 >
b100000000000000000000 =
b1 A
0"
#15000
1"
#16000
b10000000000000000000000 >
b1000000000000000000000 =
b10 A
0"
#17000
1"
#18000
b100000000000000000000000 >
b10000000000000000000000 =
b11 A
0"
#19000
1"
#20000
b1000000000000000000000000 >
b100000000000000000000000 =
b100 A
0"
#21000
1"
#22000
b10000000000000000000000000 >
b1000000000000000000000000 =
b101 A
0"
#23000
1"
#24000
b100000000000000000000000000 >
b10000000000000000000000000 =
b110 A
0"
#25000
1"
#26000
b1000000000000000000000000000 >
b100000000000000000000000000 =
b111 A
0"
#27000
1"
#28000
b10000000000000000000000000000 >
b1000000000000000000000000000 =
b1000 A
0"
#29000
1"
#30000
b100000000000000000000000000000 >
b10000000000000000000000000000 =
b1001 A
0"
#31000
1"
#32000
b1000000000000000000000000000000 >
b100000000000000000000000000000 =
b1010 A
0"
#33000
1"
#34000
b1 9
b0 >
b1000000000000000000000000000000 =
b1011 A
0"
#35000
1"
#36000
b10 9
b1 8
b0 =
b1100 A
0"
#37000
1"
#38000
b100 9
b10 8
b1101 A
0"
#39000
1"
#40000
b1000 9
b100 8
b1110 A
0"
#41000
1"
#42000
b10000 9
b1000 8
b1111 A
0"
#43000
1"
#44000
b100000 9
b10000 8
b10000 A
0"
#45000
1"
#46000
b1000000 9
b100000 8
b10001 A
0"
#47000
1"
#48000
b10000000 9
b1000000 8
b10010 A
0"
#49000
1"
#50000
b100000000 9
b10000000 8
b10011 A
0"
#51000
1"
#52000
b1000000000 9
b100000000 8
b10100 A
0"
#53000
1"
#54000
b10000000000 9
b1000000000 8
b10101 A
0"
#55000
1"
#56000
b100000000000 9
b10000000000 8
b10110 A
0"
#57000
1"
#58000
b1000000000000 9
b100000000000 8
b10111 A
0"
#59000
1"
#60000
b10000000000000 9
b1000000000000 8
b11000 A
0"
#61000
1"
#62000
b100000000000000 9
b10000000000000 8
b11001 A
0"
#63000
1"
#64000
b1000000000000000 9
b100000000000000 8
b11010 A
0"
#65000
1"
#66000
b10000000000000000 9
b1000000000000000 8
b11011 A
0"
#67000
1"
#68000
b100000000000000000 9
b10000000000000000 8
b11100 A
0"
#69000
1"
#70000
b1000000000000000000 9
b100000000000000000 8
b11101 A
0"
#71000
1"
#72000
b1 >
b0 9
b1000000000000000000 8
b11110 A
0"
#73000
1"
#74000
b10 >
b0 8
b1 =
b11111 A
0"
#75000
1"
#76000
b100 >
b10 =
b100000 A
0"
#77000
1"
#78000
b1000 >
b100 =
b100001 A
0"
#79000
1"
#80000
b10000 >
b1000 =
b100010 A
0"
#81000
1"
#82000
b100000 >
b10000 =
b100011 A
0"
#83000
1"
#84000
b1000000 >
b100000 =
b100100 A
0"
#85000
1"
#86000
b10000000 >
b1000000 =
b100101 A
0"
#87000
1"
#88000
b100000000 >
b10000000 =
b100110 A
0"
#89000
1"
#90000
b1000000000 >
b100000000 =
b100111 A
0"
#91000
1"
#92000
b10000000000 >
b1000000000 =
b101000 A
0"
#93000
1"
#94000
b100000000000 >
b10000000000 =
b101001 A
0"
#95000
1"
#96000
b1000000000000 >
b100000000000 =
b101010 A
0"
#97000
1"
#98000
b10000000000000 >
b1000000000000 =
b101011 A
0"
#99000
1"
#100000
b100000000000000 >
b10000000000000 =
b101100 A
0"
#101000
1"
#102000
b1000000000000000 >
b100000000000000 =
b101101 A
0"
#103000
1"
#104000
b10000000000000000 >
b1000000000000000 =
b101110 A
0"
#105000
1"
#106000
b101000000000000000 )
b1010000000000000000 (
b1010000000000000000 1
b1010000000000000000 3
0:
b10000000000000000 *
b10000000000000000 2
b10000000000000000 ?
1'
0"
#107000
1"
#108000
b11100000000000000 )
b111000000000000000 (
b111000000000000000 1
b111000000000000000 3
b1 /
b101000000000000000 %
b101000000000000000 0
b101000000000000000 5
b101000000000000000 +
0"
#109000
1"
#110000
b10110000000000000 )
b100000000000000000000 >
b101100000000000000 (
b101100000000000000 1
b101100000000000000 3
1:
b10000000000000000000 =
0'
b0 A
b101000000000000000 <
b10 /
b11100000000000000 %
b11100000000000000 0
b11100000000000000 5
b11100000000000000 +
0"
#111000
1"
#112000
b11100000000000000 <
0"
#113000
1"
#114000
b1000000000000000000000 >
b100000000000000000000 =
b1 A
0"
#115000
1"
#116000
b10000000000000000000000 >
b1000000000000000000000 =
b10 A
0"
#117000
1"
#118000
b100000000000000000000000 >
b10000000000000000000000 =
b11 A
0"
#119000
1"
#120000
b1000000000000000000000000 >
b100000000000000000000000 =
b100 A
0"
#121000
1"
#122000
b10000000000000000000000000 >
b1000000000000000000000000 =
b101 A
0"
#123000
1"
#124000
b100000000000000000000000000 >
b10000000000000000000000000 =
b110 A
0"
#125000
1"
#126000
b1000000000000000000000000000 >
b100000000000000000000000000 =
b111 A
0"
#127000
1"
#128000
b10000000000000000000000000000 >
b1000000000000000000000000000 =
b1000 A
0"
#129000
1"
#130000
b100000000000000000000000000000 >
b10000000000000000000000000000 =
b1001 A
0"
#131000
1"
#132000
b1000000000000000000000000000000 >
b100000000000000000000000000000 =
b1010 A
0"
#133000
1"
#134000
b1 9
b0 >
b1000000000000000000000000000000 =
b1011 A
0"
#135000
1"
#136000
b10 9
b1 8
b0 =
b1100 A
0"
#137000
1"
#138000
b100 9
b10 8
b1101 A
0"
#139000
1"
#140000
b1000 9
b100 8
b1110 A
0"
#141000
1"
#142000
b10000 9
b1000 8
b1111 A
0"
#143000
1"
#144000
b100000 9
b10000 8
b10000 A
0"
#145000
1"
#146000
b1000000 9
b100000 8
b10001 A
0"
#147000
1"
#148000
b10000000 9
b1000000 8
b10010 A
0"
#149000
1"
#150000
b100000000 9
b10000000 8
b10011 A
0"
#151000
1"
#152000
b1000000000 9
b100000000 8
b10100 A
0"
#153000
1"
#154000
b10000000000 9
b1000000000 8
b10101 A
0"
#155000
1"
#156000
b100000000000 9
b10000000000 8
b10110 A
0"
#157000
1"
#158000
b1000000000000 9
b100000000000 8
b10111 A
0"
#159000
1"
#160000
b10000000000000 9
b1000000000000 8
b11000 A
0"
#161000
1"
#162000
b100000000000000 9
b10000000000000 8
b11001 A
0"
#163000
1"
#164000
b1000000000000000 9
b100000000000000 8
b11010 A
0"
#165000
1"
#166000
b10000000000000000 9
b1000000000000000 8
b11011 A
0"
#167000
1"
#168000
b100000000000000000 9
b10000000000000000 8
b11100 A
0"
#169000
1"
#170000
b1 >
b1000000000000000 9
b100000000000000000 8
b11101 A
0"
#171000
1"
#172000
b10000000000000000 9
b10 >
b1000000000000000 8
b1 =
b11110 A
0"
#173000
1"
#174000
b100000000000000000 9
b100 >
b10000000000000000 8
b10 =
b11111 A
0"
#175000
1"
#176000
b1001 >
b1000000000000000 9
b100000000000000000 8
b100 =
b100000 A
0"
#177000
1"
#178000
b10000000000000000 9
b10010 >
b1000000000000000 8
b1001 =
b100001 A
0"
#179000
1"
#180000
b100000000000000000 9
b100100 >
b10000000000000000 8
b10010 =
b100010 A
0"
#181000
1"
#182000
b1001001 >
b1000000000000000 9
b100000000000000000 8
b100100 =
b100011 A
0"
#183000
1"
#184000
b10000000000000000 9
b10010010 >
b1000000000000000 8
b1001001 =
b100100 A
0"
#185000
1"
#186000
b100000000000000000 9
b100100100 >
b10000000000000000 8
b10010010 =
b100101 A
0"
#187000
1"
#188000
b1001001001 >
b1000000000000000 9
b100000000000000000 8
b100100100 =
b100110 A
0"
#189000
1"
#190000
b10000000000000000 9
b10010010010 >
b1000000000000000 8
b1001001001 =
b100111 A
0"
#191000
1"
#192000
b100000000000000000 9
b100100100100 >
b10000000000000000 8
b10010010010 =
b101000 A
0"
#193000
1"
#194000
b1001001001001 >
b1000000000000000 9
b100000000000000000 8
b100100100100 =
b101001 A
0"
#195000
1"
#196000
b10000000000000000 9
b10010010010010 >
b1000000000000000 8
b1001001001001 =
b101010 A
0"
#197000
1"
#198000
b100000000000000000 9
b100100100100100 >
b10000000000000000 8
b10010010010010 =
b101011 A
0"
#199000
1"
#200000
b1001001001001001 >
b1000000000000000 9
b100000000000000000 8
b100100100100100 =
b101100 A
0"
#201000
1"
#202000
b10000000000000000 9
b10010010010010010 >
b1000000000000000 8
b1001001001001001 =
b101101 A
0"
#203000
1"
#204000
b100000000000000000 9
b100100100100100100 >
b10000000000000000 8
b10010010010010010 =
b101110 A
0"
#205000
1"
#206000
b100000010010010010 )
b1000000100100100100 (
b1000000100100100100 1
b1000000100100100100 3
0:
b100100100100100100 *
b100100100100100100 2
b100100100100100100 ?
1'
0"
#207000
1"
#208000
b100010011011011011 )
b1000100110110110110 (
b1000100110110110110 1
b1000100110110110110 3
b11 /
b100000010010010010 %
b100000010010010010 0
b100000010010010010 5
b100000010010010010 +
0"
#209000
1"
#210000
b100011011111111111 )
b0 9
b100000000000000000000 >
b1000110111111111111 (
b1000110111111111111 1
b1000110111111111111 3
1:
b0 8
b10000000000000000000 =
0'
b0 A
b100000010010010010 <
b100 /
b100010011011011011 %
b100010011011011011 0
b100010011011011011 5
b100010011011011011 +
0"
#211000
1"
#212000
b100010011011011011 <
0"
#213000
1"
#214000
b1000000000000000000000 >
b100000000000000000000 =
b1 A
0"
#215000
1"
#216000
b10000000000000000000000 >
b1000000000000000000000 =
b10 A
0"
#217000
1"
#218000
b100000000000000000000000 >
b10000000000000000000000 =
b11 A
0"
#219000
1"
#220000
b1000000000000000000000000 >
b100000000000000000000000 =
b100 A
0"
#221000
1"
#222000
b10000000000000000000000000 >
b1000000000000000000000000 =
b101 A
0"
#223000
1"
#224000
b100000000000000000000000000 >
b10000000000000000000000000 =
b110 A
0"
#225000
1"
#226000
b1000000000000000000000000000 >
b100000000000000000000000000 =
b111 A
0"
#227000
1"
#228000
b10000000000000000000000000000 >
b1000000000000000000000000000 =
b1000 A
0"
#229000
1"
#230000
b100000000000000000000000000000 >
b10000000000000000000000000000 =
b1001 A
0"
#231000
1"
#232000
b1000000000000000000000000000000 >
b100000000000000000000000000000 =
b1010 A
0"
#233000
1"
#234000
b1 9
b0 >
b1000000000000000000000000000000 =
b1011 A
0"
#235000
1"
#236000
b10 9
b1 8
b0 =
b1100 A
0"
#237000
1"
#238000
b100 9
b10 8
b1101 A
0"
#239000
1"
#240000
b1000 9
b100 8
b1110 A
0"
#241000
1"
#242000
b10000 9
b1000 8
b1111 A
0"
#243000
1"
#244000
b100000 9
b10000 8
b10000 A
0"
#245000
1"
#246000
b1000000 9
b100000 8
b10001 A
0"
#247000
1"
#248000
b10000000 9
b1000000 8
b10010 A
0"
#249000
1"
#250000
b100000000 9
b10000000 8
b10011 A
0"
#251000
1"
#252000
b1000000000 9
b100000000 8
b10100 A
0"
#253000
1"
#254000
b10000000000 9
b1000000000 8
b10101 A
0"
#255000
1"
#256000
b100000000000 9
b10000000000 8
b10110 A
0"
#257000
1"
#258000
b1000000000000 9
b100000000000 8
b10111 A
0"
#259000
1"
#260000
b10000000000000 9
b1000000000000 8
b11000 A
0"
#261000
1"
#262000
b100000000000000 9
b10000000000000 8
b11001 A
0"
#263000
1"
#264000
b1000000000000000 9
b100000000000000 8
b11010 A
0"
#265000
1"
#266000
b10000000000000000 9
b1000000000000000 8
b11011 A
0"
#267000
1"
#268000
b100000000000000000 9
b10000000000000000 8
b11100 A
0"
#269000
1"
#270000
b1000000000000000000 9
b100000000000000000 8
b11101 A
0"
#271000
1"
#272000
b1 >
b111011001001001010 9
b1000000000000000000 8
b11110 A
0"
#273000
1"
#274000
b11 >
b110001011011011110 9
b111011001001001010 8
b1 =
b11111 A
0"
#275000
1"
#276000
b111 >
b11110000000000110 9
b110001011011011110 8
b11 =
b100000 A
0"
#277000
1"
#278000
b111100000000001100 9
b1110 >
b11110000000000110 8
b111 =
b100001 A
0"
#279000
1"
#280000
b11101 >
b110011001001100010 9
b111100000000001100 8
b1110 =
b100010 A
0"
#281000
1"
#282000
b111011 >
b100001011100001110 9
b110011001001100010 8
b11101 =
b100011 A
0"
#283000
1"
#284000
b1000010111000011100 9
b1110110 >
b100001011100001110 8
b111011 =
b100100 A
0"
#285000
1"
#286000
b11101101 >
b1000000111010000010 9
b1000010111000011100 8
b1110110 =
b100101 A
0"
#287000
1"
#288000
b111011011 >
b111100111101001110 9
b1000000111010000010 8
b11101101 =
b100110 A
0"
#289000
1"
#290000
b1110110111 >
b110101000011100110 9
b111100111101001110 8
b111011011 =
b100111 A
0"
#291000
1"
#292000
b11101101111 >
b100101010000010110 9
b110101000011100110 8
b1110110111 =
b101000 A
0"
#293000
1"
#294000
b111011011111 >
b101101001110110 9
b100101010000010110 8
b11101101111 =
b101001 A
0"
#295000
1"
#296000
b1011010011101100 9
b1110110111110 >
b101101001110110 8
b111011011111 =
b101010 A
0"
#297000
1"
#298000
b10110100111011000 9
b11101101111100 >
b1011010011101100 8
b1110110111110 =
b101011 A
0"
#299000
1"
#300000
b101101001110110000 9
b111011011111000 >
b10110100111011000 8
b11101101111100 =
b101100 A
0"
#301000
1"
#302000
b1110110111110001 >
b10101100110101010 9
b101101001110110000 8
b111011011111000 =
b101101 A
0"
#303000
1"
#304000
b101011001101010100 9
b11101101111100010 >
b10101100110101010 8
b1110110111110001 =
b101110 A
0"
#305000
1"
#306000
b100000000101011110 )
b1000000001010111101 (
b1000000001010111101 1
b1000000001010111101 3
0:
b11101101111100010 *
b11101101111100010 2
b11101101111100010 ?
1'
0"
#307000
1"
#308000
b11110111010100000 )
b111101110101000000 (
b111101110101000000 1
b111101110101000000 3
b101 /
b100000000101011110 %
b100000000101011110 0
b100000000101011110 5
b100000000101011110 +
0"
#309000
1"
#310000
b11110010101000001 )
b0 9
b100000000000000000000 >
b111100101010000010 (
b111100101010000010 1
b111100101010000010 3
1:
b0 8
b10000000000000000000 =
0'
b0 A
b100000000101011110 <
b110 /
b11110111010100000 %
b11110111010100000 0
b11110111010100000 5
b11110111010100000 +
0"
#311000
1"
#312000
b11110111010100000 <
0"
#313000
1"
#314000
b1000000000000000000000 >
b100000000000000000000 =
b1 A
0"
#315000
1"
#316000
b10000000000000000000000 >
b1000000000000000000000 =
b10 A
0"
#317000
1"
#318000
b100000000000000000000000 >
b10000000000000000000000 =
b11 A
0"
#319000
1"
#320000
b1000000000000000000000000 >
b100000000000000000000000 =
b100 A
0"
#321000
1"
#322000
b10000000000000000000000000 >
b1000000000000000000000000 =
b101 A
0"
#323000
1"
#324000
b100000000000000000000000000 >
b10000000000000000000000000 =
b110 A
0"
#325000
1"
#326000
b1000000000000000000000000000 >
b100000000000000000000000000 =
b111 A
0"
#327000
1"
#328000
b10000000000000000000000000000 >
b1000000000000000000000000000 =
b1000 A
0"
#329000
1"
#330000
b100000000000000000000000000000 >
b10000000000000000000000000000 =
b1001 A
0"
#331000
1"
#332000
b1000000000000000000000000000000 >
b100000000000000000000000000000 =
b1010 A
0"
#333000
1"
#334000
b1 9
b0 >
b1000000000000000000000000000000 =
b1011 A
0"
#335000
1"
#336000
b10 9
b1 8
b0 =
b1100 A
0"
#337000
1"
#338000
b100 9
b10 8
b1101 A
0"
#339000
1"
#340000
b1000 9
b100 8
b1110 A
0"
#341000
1"
#342000
b10000 9
b1000 8
b1111 A
0"
#343000
1"
#344000
b100000 9
b10000 8
b10000 A
0"
#345000
1"
#346000
b1000000 9
b100000 8
b10001 A
0"
#347000
1"
#348000
b10000000 9
b1000000 8
b10010 A
0"
#349000
1"
#350000
b100000000 9
b10000000 8
b10011 A
0"
#351000
1"
#352000
b1000000000 9
b100000000 8
b10100 A
0"
#353000
1"
#354000
b10000000000 9
b1000000000 8
b10101 A
0"
#355000
1"
#356000
b100000000000 9
b10000000000 8
b10110 A
0"
#357000
1"
#358000
b1000000000000 9
b100000000000 8
b10111 A
0"
#359000
1"
#360000
b10000000000000 9
b1000000000000 8
b11000 A
0"
#361000
1"
#362000
b100000000000000 9
b10000000000000 8
b11001 A
0"
#363000
1"
#364000
b1000000000000000 9
b100000000000000 8
b11010 A
0"
#365000
1"
#366000
b10000000000000000 9
b1000000000000000 8
b11011 A
0"
#367000
1"
#368000
b100000000000000000 9
b10000000000000000 8
b11100 A
0"
#369000
1"
#370000
b1 >
b10001011000000 9
b100000000000000000 8
b11101 A
0"
#371000
1"
#372000
b100010110000000 9
b10 >
b10001011000000 8
b1 =
b11110 A
0"
#373000
1"
#374000
b1000101100000000 9
b100 >
b100010110000000 8
b10 =
b11111 A
0"
#375000
1"
#376000
b10001011000000000 9
b1000 >
b1000101100000000 8
b100 =
b100000 A
0"
#377000
1"
#378000
b100010110000000000 9
b10000 >
b10001011000000000 8
b1000 =
b100001 A
0"
#379000
1"
#380000
b100001 >
b111101011000000 9
b100010110000000000 8
b10000 =
b100010 A
0"
#381000
1"
#382000
b1111010110000000 9
b1000010 >
b111101011000000 8
b100001 =
b100011 A
0"
#383000
1"
#384000
b11110101100000000 9
b10000100 >
b1111010110000000 8
b1000010 =
b100100 A
0"
#385000
1"
#386000
b111101011000000000 9
b100001000 >
b11110101100000000 8
b10000100 =
b100101 A
0"
#387000
1"
#388000
b1000010001 >
b111100111011000000 9
b111101011000000000 8
b100001000 =
b100110 A
0"
#389000
1"
#390000
b10000100011 >
b111100000001000000 9
b111100111011000000 8
b1000010001 =
b100111 A
0"
#391000
1"
#392000
b100001000111 >
b111010001101000000 9
b111100000001000000 8
b10000100011 =
b101000 A
0"
#393000
1"
#394000
b1000010001111 >
b110110100101000000 9
b111010001101000000 8
b100001000111 =
b101001 A
0"
#395000
1"
#396000
b10000100011111 >
b101111010101000000 9
b110110100101000000 8
b1000010001111 =
b101010 A
0"
#397000
1"
#398000
b100001000111111 >
b100000110101000000 9
b101111010101000000 8
b10000100011111 =
b101011 A
0"
#399000
1"
#400000
b1000010001111111 >
b11110101000000 9
b100000110101000000 8
b100001000111111 =
b101100 A
0"
#401000
1"
#402000
b111101010000000 9
b10000100011111110 >
b11110101000000 8
b1000010001111111 =
b101101 A
0"
#403000
1"
#404000
b1111010100000000 9
b100001000111111100 >
b111101010000000 8
b10000100011111110 =
b101110 A
0"
#405000
1"
#406000
b100000000001001110 )
b1000000000010011100 (
b1000000000010011100 1
b1000000000010011100 3
0:
b100001000111111100 *
b100001000111111100 2
b100001000111111100 ?
1'
0"
#407000
1"
#408000
b100000100100100101 )
b1000001001001001010 (
b1000001001001001010 1
b1000001001001001010 3
b111 /
b100000000001001110 %
b100000000001001110 0
b100000000001001110 5
b100000000001001110 +
0"
#409000
1"
#410000
b100000110110010000 )
b0 9
b100000000000000000000 >
b1000001101100100001 (
b1000001101100100001 1
b1000001101100100001 3
1:
b0 8
b10000000000000000000 =
0'
b0 A
b100000000001001110 <
b1000 /
b100000100100100101 %
b100000100100100101 0
b100000100100100101 5
b100000100100100101 +
0"
#411000
1"
#412000
b100000100100100101 <
0"
#413000
1"
#414000
b1000000000000000000000 >
b100000000000000000000 =
b1 A
0"
#415000
1"
#416000
b10000000000000000000000 >
b1000000000000000000000 =
b10 A
0"
#417000
1"
#418000
b100000000000000000000000 >
b10000000000000000000000 =
b11 A
0"
#419000
1"
#420000
b1000000000000000000000000 >
b100000000000000000000000 =
b100 A
0"
#421000
1"
#422000
b10000000000000000000000000 >
b1000000000000000000000000 =
b101 A
0"
#423000
1"
#424000
b100000000000000000000000000 >
b10000000000000000000000000 =
b110 A
0"
#425000
1"
#426000
b1000000000000000000000000000 >
b100000000000000000000000000 =
b111 A
0"
#427000
1"
#428000
b10000000000000000000000000000 >
b1000000000000000000000000000 =
b1000 A
0"
#429000
1"
#430000
b100000000000000000000000000000 >
b10000000000000000000000000000 =
b1001 A
0"
#431000
1"
#432000
b1000000000000000000000000000000 >
b100000000000000000000000000000 =
b1010 A
0"
#433000
1"
#434000
b1 9
b0 >
b1000000000000000000000000000000 =
b1011 A
0"
#435000
1"
#436000
b10 9
b1 8
b0 =
b1100 A
0"
#437000
1"
#438000
b100 9
b10 8
b1101 A
0"
#439000
1"
#440000
b1000 9
b100 8
b1110 A
0"
#441000
1"
#442000
b10000 9
b1000 8
b1111 A
0"
#443000
1"
#444000
b100000 9
b10000 8
b10000 A
0"
#445000
1"
#446000
b1000000 9
b100000 8
b10001 A
0"
#447000
1"
#448000
b10000000 9
b1000000 8
b10010 A
0"
#449000
1"
#450000
b100000000 9
b10000000 8
b10011 A
0"
#451000
1"
#452000
b1000000000 9
b100000000 8
b10100 A
0"
#453000
1"
#454000
b10000000000 9
b1000000000 8
b10101 A
0"
#455000
1"
#456000
b100000000000 9
b10000000000 8
b10110 A
0"
#457000
1"
#458000
b1000000000000 9
b100000000000 8
b10111 A
0"
#459000
1"
#460000
b10000000000000 9
b1000000000000 8
b11000 A
0"
#461000
1"
#462000
b100000000000000 9
b10000000000000 8
b11001 A
0"
#463000
1"
#464000
b1000000000000000 9
b100000000000000 8
b11010 A
0"
#465000
1"
#466000
b10000000000000000 9
b1000000000000000 8
b11011 A
0"
#467000
1"
#468000
b100000000000000000 9
b10000000000000000 8
b11100 A
0"
#469000
1"
#470000
b1000000000000000000 9
b100000000000000000 8
b11101 A
0"
#471000
1"
#472000
b1 >
b111110110110110110 9
b1000000000000000000 8
b11110 A
0"
#473000
1"
#474000
b11 >
b111100100100100010 9
b111110110110110110 8
b1 =
b11111 A
0"
#475000
1"
#476000
b111 >
b110111111111111010 9
b111100100100100010 8
b11 =
b100000 A
0"
#477000
1"
#478000
b1111 >
b101110110110101010 9
b110111111111111010 8
b111 =
b100001 A
0"
#479000
1"
#480000
b11111 >
b11100100100001010 9
b101110110110101010 8
b1111 =
b100010 A
0"
#481000
1"
