user/src/basic/qmulti.v
`ifndef QMULTI_V
`define QMULTI_V
module qmulti(
    input [31:0] multi1,
    input [31:0] multi2,
    output [31:0] result
);

reg [63:0] tmp=0;
reg [31:0] result_out=0;

assign result=result_out;

always @(*) 
begin
    tmp=multi1[30:0]*multi2[30:0];
    if(multi1[31]==multi2[31])
    begin
        result_out={1'b0,tmp[46:16]};
    end
    else
    begin
        result_out={1'b1,tmp[46:16]};
    end
end

endmodule
`endif

user/src/basic/qadd.v
//小数加法器，32位数据，31位为符号位，30-16位为整数位，15-0位为小数位
//输入：加数32位的add1,add2
//输出：和数32位的sum
`ifndef QADD_V
`define QADD_V
module qadd
(
    input [31:0] add1,
    input [31:0] add2,
    output [31:0] sum
);
    reg[31:0] res=0;//暂存加的结果

    assign sum = res;

    always @(*) 
    begin
        if(add1[31]==add2[31])//同号相加
        begin
            res[31] = add1[31];
            if(add1[30:0]+add2[30:0]>=2**31)//判断是否溢出
            begin
                res[30:0] = add1[30:0]+add2[30:0]-2**31;
            end
            else
            begin
                res[30:0] = add1[30:0]+add2[30:0];
            end
        end
        else//异号则数字位相减
        begin
            if(add1[30:0]>add2[30:0])
            begin
                res[31] = add1[31];
                res[30:0] = add1[30:0]-add2[30:0];
            end
            else if(add1[30:0]<add2[30:0])
            begin
                res[31] = add2[31];
                res[30:0] = add2[30:0]-add1[30:0];
            end
            else
            begin
                res[31] = 1'b0;
                res[30:0] = 0;
            end
        end
    end
endmodule
`endif

user/src/basic/qdiv.v
`ifndef QDIV_V
`define QDIV_V

module qdiv(
    input clk,
    input rst_n,
    input [31:0] dividend,
    input [31:0] divisor,
    output reg [31:0] quotient,
    output reg valid,//运算完成信号
    output reg warn,//除数为0警告
    output reg busy//运算中信号
    );

    parameter WIDTH = 31;
    parameter  FBITS = 16;

    wire [WIDTH-1:0] dividend_unsigned;
    wire [WIDTH-1:0] divisor_unsigned;

    integer i=0;

    reg [WIDTH-1:0] dividend_reg;//被除数寄存器(不带符号)
    reg [WIDTH-1:0] divisor_reg;//除数寄存器(不带符号)
    reg [WIDTH:0] acc;//单次被除数
    reg [WIDTH-1:0] quo;//实际使用中移位的被除数和商(复用)

    reg [WIDTH:0] acc_next;//单次被除数下一个
    reg [WIDTH-1:0] quo_next;//实际使用中移位的被除数下一个

    assign dividend_unsigned=dividend[WIDTH-1:0];
    assign divisor_unsigned=divisor[WIDTH-1:0];

    always @(*) 
    begin
      if (acc >= {1'b0, divisor_reg}) 
      begin
        acc_next = acc - divisor_reg;
        {acc_next, quo_next} = {acc_next[WIDTH-1:0], quo, 1'b1};
      end 
      else 
      begin
        {acc_next, quo_next} = {acc, quo} << 1;
      end
    end

    always @(posedge clk or negedge rst_n) 
    begin
        if(!rst_n)
        begin
            dividend_reg <= 0;
            divisor_reg <= 0;
            quotient <= 0;
            valid <= 0;
            warn <= 0;
            acc <= 0;
            quo <= 0;
            busy <= 0;

            //acc_next <= 0;
            //quo_next <= 0;
        end
        else if(divisor==0)
        begin
            warn <= 1;
            valid <= 0;
            quotient <= 0;
            busy <= 0;
        end
        else
        begin
            dividend_reg <= dividend_unsigned;
            divisor_reg <= divisor_unsigned;
            if(dividend_unsigned!=dividend_reg||divisor_unsigned!=divisor_reg)//输入变化，重新计算
            begin
                i <= 0;
                valid <= 0;
                {acc, quo} <= {{WIDTH{1'b0}}, dividend_unsigned, 1'b0};
                busy <= 1'b1;
            end
            else
            begin
                if(i==WIDTH+FBITS-1)
                begin
                    valid<=1;
                    busy <= 1'b0;
                    if(dividend[WIDTH]==divisor[WIDTH])
                      quotient<={1'b0,quo_next[WIDTH-1:0]};
                    else
                      quotient<={1'b1,quo_next[WIDTH-1:0]};
                end
                else
                begin
                    i<=i+1;
                    {acc, quo} <= {acc_next, quo_next};
                end
            end
        end
    end
endmodule
`endif

user/src/basic/sqrt.v
//`include "../qmulti/qmulti.v"
//`include "../qdiv/qdiv.v"
//`include "../qadd/qadd.v"
`ifndef SQRT_V
`define SQRT_V
module sqrt(
    input clk,
    input rst_n,
    output reg valid,

    input [31:0] sqrter,
    output reg [31:0] sqrted
);

    wire [31:0] iter;
    wire [31:0] two;
    wire [31:0] dived;
    wire [31:0] sum;
    wire [31:0] iter_next;
    wire valid_dived;

    reg [31:0] sqrter_reg;
    reg [31:0] iter_reg;

    integer i=0;
    
    assign iter = iter_reg;
    assign iter_next = sum>>1;

    qdiv 
    qdiv_dut1 (
        .clk (clk ),
        .rst_n (rst_n ),
        .valid(valid_dived),
        .busy(),
        .dividend (sqrter ),
        .divisor (iter ),
        .quotient (dived ),
        .warn  ( )
    );
    qadd
    qadd_dut (
        .add1 (dived ),
        .add2 (iter ),
        .sum (sum )
    );

    always @(posedge clk or negedge rst_n) 
    begin
        if(rst_n==0)
        begin
            sqrter_reg <= 0;
            sqrted <= 0;
            i <= 0;
            valid <= 0;
            iter_reg <= 0;
        end
        else
        begin
            sqrter_reg <= sqrter;
            if(sqrter_reg != sqrter)
            begin
                i <= 0;
                iter_reg <= sqrter;
                valid <= 0;
            end
            else if(i == 21)
            begin
                sqrted <= iter;
                valid <= 1;
            end
            else
            begin
                if(valid_dived)
                begin
                    iter_reg <= iter_next;
                    i <= i+1;
                end
            end
        end
    end

endmodule
`endif

user/sim/basic/sqrt_tb.v
`timescale 1ns / 1ps
module sqrt_tb;

// Parameters

// Ports
reg clk = 0;
reg rst_n = 0;
reg [31:0] sqrter;
wire [31:0] sqrted;

sqrt 
sqrt_dut (
  .clk (clk ),
  .rst_n (rst_n ),
  .sqrter (sqrter ),
  .sqrted  ( sqrted)
);

initial begin
  begin
      $dumpfile("sqrt_tb.vcd");
      $dumpvars(0, sqrt_tb);
      rst_n=0;
      #10
      rst_n=1;
      sqrter=32'h00040000;
      #10000
      sqrter=32'h00070000;
      #10000
      sqrter=32'h00100000;
      #10000
      $finish;
  end
end

always
  #1  clk = ! clk ;

endmodule

sqrt_tb.vcd
$date
	Tue Jul 04 10:45:01 2023
$end
$version
	Icarus Verilog
$end
$timescale
	1ps
$end
$scope module sqrt_tb $end
$var wire 32 ! sqrted [31:0] $end
$var reg 1 " clk $end
$var reg 1 # rst_n $end
$var reg 32 $ sqrter [31:0] $end
$scope module sqrt_dut $end
$var wire 1 " clk $end
$var wire 1 # rst_n $end
$var wire 32 % sqrter [31:0] $end
$var wire 1 & valid_dived $end
$var wire 32 ' sum [31:0] $end
$var wire 32 ( iter_next [31:0] $end
$var wire 32 ) iter [31:0] $end
$var wire 32 * dived [31:0] $end
$var reg 32 + iter_reg [31:0] $end
$var reg 32 , sqrted [31:0] $end
$var reg 32 - sqrter_reg [31:0] $end
$var reg 1 . valid $end
$var integer 32 / i [31:0] $end
$scope module qadd_dut $end
$var wire 32 0 add2 [31:0] $end
$var wire 32 1 sum [31:0] $end
$var wire 32 2 add1 [31:0] $end
$var reg 32 3 res [31:0] $end
$upscope $end
$scope module qdiv_dut1 $end
$var wire 1 " clk $end
$var wire 32 4 dividend [31:0] $end
$var wire 32 5 divisor [31:0] $end
$var wire 1 # rst_n $end
$var wire 31 6 divisor_unsigned [30:0] $end
$var wire 31 7 dividend_unsigned [30:0] $end
$var parameter 32 8 FBITS $end
$var parameter 32 9 WIDTH $end
$var reg 32 : acc [31:0] $end
$var reg 32 ; acc_next [31:0] $end
$var reg 1 < busy $end
$var reg 31 = dividend_reg [30:0] $end
$var reg 31 > divisor_reg [30:0] $end
$var reg 31 ? quo [30:0] $end
$var reg 31 @ quo_next [30:0] $end
$var reg 32 A quotient [31:0] $end
$var reg 1 & valid $end
$var reg 1 B warn $end
$var integer 32 C i [31:0] $end
$upscope $end
$upscope $end
$upscope $end
$enddefinitions $end
$comment Show the parameter values. $end
$dumpall
b11111 9
b10000 8
$end
#0
$dumpvars
b0 C
xB
bx A
bx @
bx ?
bx >
bx =
x<
bx ;
bx :
bx 7
bx 6
bx 5
bx 4
b0 3
bx 2
b0 1
bx 0
b0 /
x.
bx -
bx ,
bx +
bx *
bx )
b0 (
b0 '
x&
bx %
bx $
0#
0"
bx !
$end
#1000
b1 @
b0 ;
b0 6
0<
b0 ?
b0 :
0B
0&
b0 *
b0 2
b0 A
b0 >
b0 =
b0 )
b0 +
b0 0
b0 5
0.
b0 !
b0 ,
b0 -
1"
#2000
0"
#3000
1"
#4000
0"
#5000
1"
#6000
0"
#7000
1"
#8000
0"
#9000
1"
#10000
b1000000000000000000 7
0"
b1000000000000000000 $
b1000000000000000000 %
b1000000000000000000 4
1#
#11000
b100000000000000000 (
b1000000000000000000 '
b1000000000000000000 1
b1000000000000000000 3
b1000000000000000000 6
b1000000000000000000 )
b1000000000000000000 +
b1000000000000000000 0
b1000000000000000000 5
b1000000000000000000 -
1B
1"
#12000
0"
#13000
b100000000000000000000 @
1<
b10000000000000000000 ?
b1000000000000000000 >
b1000000000000000000 =
1"
#14000
0"
#15000
b1000000000000000000000 @
b100000000000000000000 ?
b1 C
1"
#16000
0"
#17000
b10000000000000000000000 @
b1000000000000000000000 ?
b10 C
1"
#18000
0"
#19000
b100000000000000000000000 @
b10000000000000000000000 ?
b11 C
1"
#20000
0"
#21000
b1000000000000000000000000 @
b100000000000000000000000 ?
b100 C
1"
#22000
0"
#23000
b10000000000000000000000000 @
b1000000000000000000000000 ?
b101 C
1"
#24000
0"
#25000
b100000000000000000000000000 @
b10000000000000000000000000 ?
b110 C
1"
#26000
0"
#27000
b1000000000000000000000000000 @
b100000000000000000000000000 ?
b111 C
1"
#28000
0"
#29000
b10000000000000000000000000000 @
b1000000000000000000000000000 ?
b1000 C
1"
#30000
0"
#31000
b100000000000000000000000000000 @
b10000000000000000000000000000 ?
b1001 C
1"
#32000
0"
#33000
b1000000000000000000000000000000 @
b100000000000000000000000000000 ?
b1010 C
1"
#34000
0"
#35000
b1 ;
b0 @
b1000000000000000000000000000000 ?
b1011 C
1"
#36000
0"
#37000
b10 ;
b1 :
b0 ?
b1100 C
1"
#38000
0"
#39000
b100 ;
b10 :
b1101 C
1"
#40000
0"
#41000
b1000 ;
b100 :
b1110 C
1"
#42000
0"
#43000
b10000 ;
b1000 :
b1111 C
1"
#44000
0"
#45000
b100000 ;
b10000 :
b10000 C
1"
#46000
0"
#47000
b1000000 ;
b100000 :
b10001 C
1"
#48000
0"
#49000
b10000000 ;
b1000000 :
b10010 C
1"
#50000
0"
#51000
b100000000 ;
b10000000 :
b10011 C
1"
#52000
0"
#53000
b1000000000 ;
b100000000 :
b10100 C
1"
#54000
0"
#55000
b10000000000 ;
b1000000000 :
b10101 C
1"
#56000
0"
#57000
b100000000000 ;
b10000000000 :
b10110 C
1"
#58000
0"
#59000
b1000000000000 ;
b100000000000 :
b10111 C
1"
#60000
0"
#61000
b10000000000000 ;
b1000000000000 :
b11000 C
1"
#62000
0"
#63000
b100000000000000 ;
b10000000000000 :
b11001 C
1"
#64000
0"
#65000
b1000000000000000 ;
b100000000000000 :
b11010 C
1"
#66000
0"
#67000
b10000000000000000 ;
b1000000000000000 :
b11011 C
1"
#68000
0"
#69000
b100000000000000000 ;
b10000000000000000 :
b11100 C
1"
#70000
0"
#71000
b1000000000000000000 ;
b100000000000000000 :
b11101 C
1"
#72000
0"
#73000
b1 @
b0 ;
b1000000000000000000 :
b11110 C
1"
#74000
0"
#75000
b10 @
b0 :
b1 ?
b11111 C
1"
#76000
0"
#77000
b100 @
b10 ?
b100000 C
1"
#78000
0"
#79000
b1000 @
b100 ?
b100001 C
1"
#80000
0"
#81000
b10000 @
b1000 ?
b100010 C
1"
#82000
0"
#83000
b100000 @
b10000 ?
b100011 C
1"
#84000
0"
#85000
b1000000 @
b100000 ?
b100100 C
1"
#86000
0"
#87000
b10000000 @
b1000000 ?
b100101 C
1"
#88000
0"
#89000
b100000000 @
b10000000 ?
b100110 C
1"
#90000
0"
#91000
b1000000000 @
b100000000 ?
b100111 C
1"
#92000
0"
#93000
b10000000000 @
b1000000000 ?
b101000 C
1"
#94000
0"
#95000
b100000000000 @
b10000000000 ?
b101001 C
1"
#96000
0"
#97000
b1000000000000 @
b100000000000 ?
b101010 C
1"
#98000
0"
#99000
b10000000000000 @
b1000000000000 ?
b101011 C
1"
#100000
0"
#101000
b100000000000000 @
b10000000000000 ?
b101100 C
1"
#102000
0"
#103000
b1000000000000000 @
b100000000000000 ?
b101101 C
1"
#104000
0"
#105000
b10000000000000000 @
b1000000000000000 ?
b101110 C
1"
#106000
0"
#107000
b101000000000000000 (
b1010000000000000000 '
b1010000000000000000 1
b1010000000000000000 3
b10000000000000000 *
b10000000000000000 2
b10000000000000000 A
0<
1&
1"
#108000
0"
#109000
b11100000000000000 (
b111000000000000000 '
b111000000000000000 1
b111000000000000000 3
b101000000000000000 6
b1 /
b101000000000000000 )
b101000000000000000 +
b101000000000000000 0
b101000000000000000 5
1"
#110000
0"
#111000
b10110000000000000 (
b101100000000000000 '
b101100000000000000 1
b101100000000000000 3
b11100000000000000 6
b100000000000000000000 @
b10 /
b11100000000000000 )
b11100000000000000 +
b11100000000000000 0
b11100000000000000 5
1<
b10000000000000000000 ?
0&
b0 C
b101000000000000000 >
1"
#112000
0"
#113000
b11100000000000000 >
1"
#114000
0"
#115000
b1000000000000000000000 @
b100000000000000000000 ?
b1 C
1"
#116000
0"
#117000
b10000000000000000000000 @
b1000000000000000000000 ?
b10 C
1"
#118000
0"
#119000
b100000000000000000000000 @
b10000000000000000000000 ?
b11 C
1"
#120000
0"
#121000
b1000000000000000000000000 @
b100000000000000000000000 ?
b100 C
1"
#122000
0"
#123000
b10000000000000000000000000 @
b1000000000000000000000000 ?
b101 C
1"
#124000
0"
#125000
b100000000000000000000000000 @
b10000000000000000000000000 ?
b110 C
1"
#126000
0"
#127000
b1000000000000000000000000000 @
b100000000000000000000000000 ?
b111 C
1"
#128000
0"
#129000
b10000000000000000000000000000 @
b1000000000000000000000000000 ?
b1000 C
1"
#130000
0"
#131000
b100000000000000000000000000000 @
b10000000000000000000000000000 ?
b1001 C
1"
#132000
0"
#133000
b1000000000000000000000000000000 @
b100000000000000000000000000000 ?
b1010 C
1"
#134000
0"
#135000
b1 ;
b0 @
b1000000000000000000000000000000 ?
b1011 C
1"
#136000
0"
#137000
b10 ;
b1 :
b0 ?
b1100 C
1"
#138000
0"
#139000
b100 ;
b10 :
b1101 C
1"
#140000
0"
#141000
b1000 ;
b100 :
b1110 C
1"
#142000
0"
#143000
b10000 ;
b1000 :
b1111 C
1"
#144000
0"
#145000
b100000 ;
b10000 :
b10000 C
1"
#146000
0"
#147000
b1000000 ;
b100000 :
b10001 C
1"
#148000
0"
#149000
b10000000 ;
b1000000 :
b10010 C
1"
#150000
0"
#151000
b100000000 ;
b10000000 :
b10011 C
1"
#152000
0"
#153000
b1000000000 ;
b100000000 :
b10100 C
1"
#154000
0"
#155000
b10000000000 ;
b1000000000 :
b10101 C
1"
#156000
0"
#157000
b100000000000 ;
b10000000000 :
b10110 C
1"
#158000
0"
#159000
b1000000000000 ;
b100000000000 :
b10111 C
1"
#160000
0"
#161000
b10000000000000 ;
b1000000000000 :
b11000 C
1"
#162000
0"
#163000
b100000000000000 ;
b10000000000000 :
b11001 C
1"
#164000
0"
#165000
b1000000000000000 ;
b100000000000000 :
b11010 C
1"
#166000
0"
#167000
b10000000000000000 ;
b1000000000000000 :
b11011 C
1"
#168000
0"
#169000
b100000000000000000 ;
b10000000000000000 :
b11100 C
1"
#170000
0"
#171000
b1 @
b1000000000000000 ;
b100000000000000000 :
b11101 C
1"
#172000
0"
#173000
b10000000000000000 ;
b10 @
b1000000000000000 :
b1 ?
b11110 C
1"
#174000
0"
#175000
b100000000000000000 ;
b100 @
b10000000000000000 :
b10 ?
b11111 C
1"
#176000
0"
#177000
b1001 @
b1000000000000000 ;
b100000000000000000 :
b100 ?
b100000 C
1"
#178000
0"
#179000
b10000000000000000 ;
b10010 @
b1000000000000000 :
b1001 ?
b100001 C
1"
#180000
0"
#181000
b100000000000000000 ;
b100100 @
b10000000000000000 :
b10010 ?
b100010 C
1"
#182000
0"
#183000
b1001001 @
b1000000000000000 ;
b100000000000000000 :
b100100 ?
b100011 C
1"
#184000
0"
#185000
b10000000000000000 ;
b10010010 @
b1000000000000000 :
b1001001 ?
b100100 C
1"
#186000
0"
#187000
b100000000000000000 ;
b100100100 @
b10000000000000000 :
b10010010 ?
b100101 C
1"
#188000
0"
#189000
b1001001001 @
b1000000000000000 ;
b100000000000000000 :
b100100100 ?
b100110 C
1"
#190000
0"
#191000
b10000000000000000 ;
b10010010010 @
b1000000000000000 :
b1001001001 ?
b100111 C
1"
#192000
0"
#193000
b100000000000000000 ;
b100100100100 @
b10000000000000000 :
b10010010010 ?
b101000 C
1"
#194000
0"
#195000
b1001001001001 @
b1000000000000000 ;
b100000000000000000 :
b100100100100 ?
b101001 C
1"
#196000
0"
#197000
b10000000000000000 ;
b10010010010010 @
b1000000000000000 :
b1001001001001 ?
b101010 C
1"
#198000
0"
#199000
b100000000000000000 ;
b100100100100100 @
b10000000000000000 :
b10010010010010 ?
b101011 C
1"
#200000
0"
#201000
b1001001001001001 @
b1000000000000000 ;
b100000000000000000 :
b100100100100100 ?
b101100 C
1"
#202000
0"
#203000
b10000000000000000 ;
b10010010010010010 @
b1000000000000000 :
b1001001001001001 ?
b101101 C
1"
#204000
0"
#205000
b100000000000000000 ;
b100100100100100100 @
b10000000000000000 :
b10010010010010010 ?
b101110 C
1"
#206000
0"
#207000
b100000010010010010 (
b1000000100100100100 '
b1000000100100100100 1
b1000000100100100100 3
b100100100100100100 *
b100100100100100100 2
b100100100100100100 A
0<
1&
1"
#208000
0"
#209000
b100010011011011011 (
b1000100110110110110 '
b1000100110110110110 1
b1000100110110110110 3
b100000010010010010 6
b11 /
b100000010010010010 )
b100000010010010010 +
b100000010010010010 0
b100000010010010010 5
1"
#210000
0"
#211000
b100011011111111111 (
b1000110111111111111 '
b1000110111111111111 1
b1000110111111111111 3
b100010011011011011 6
b0 ;
b100000000000000000000 @
b100 /
b100010011011011011 )
b100010011011011011 +
b100010011011011011 0
b100010011011011011 5
1<
b0 :
b10000000000000000000 ?
0&
b0 C
b100000010010010010 >
1"
#212000
0"
#213000
b100010011011011011 >
1"
#214000
0"
#215000
b1000000000000000000000 @
b100000000000000000000 ?
b1 C
1"
#216000
0"
#217000
b10000000000000000000000 @
b1000000000000000000000 ?
b10 C
1"
#218000
0"
#219000
b100000000000000000000000 @
b10000000000000000000000 ?
b11 C
1"
#220000
0"
#221000
b1000000000000000000000000 @
b100000000000000000000000 ?
b100 C
1"
#222000
0"
#223000
b10000000000000000000000000 @
b1000000000000000000000000 ?
b101 C
1"
#224000
0"
#225000
b100000000000000000000000000 @
b10000000000000000000000000 ?
b110 C
1"
#226000
0"
#227000
b1000000000000000000000000000 @
b100000000000000000000000000 ?
b111 C
1"
#228000
0"
#229000
b10000000000000000000000000000 @
b1000000000000000000000000000 ?
b1000 C
1"
#230000
0"
#231000
b100000000000000000000000000000 @
b10000000000000000000000000000 ?
b1001 C
1"
#232000
0"
#233000
b1000000000000000000000000000000 @
b100000000000000000000000000000 ?
b1010 C
1"
#234000
0"
#235000
b1 ;
b0 @
b1000000000000000000000000000000 ?
b1011 C
1"
#236000
0"
#237000
b10 ;
b1 :
b0 ?
b1100 C
1"
#238000
0"
#239000
b100 ;
b10 :
b1101 C
1"
#240000
0"
#241000
b1000 ;
b100 :
b1110 C
1"
#242000
0"
#243000
b10000 ;
b1000 :
b1111 C
1"
#244000
0"
#245000
b100000 ;
b10000 :
b10000 C
1"
#246000
0"
#247000
b1000000 ;
b100000 :
b10001 C
1"
#248000
0"
#249000
b10000000 ;
b1000000 :
b10010 C
1"
#250000
0"
#251000
b100000000 ;
b10000000 :
b10011 C
1"
#252000
0"
#253000
b1000000000 ;
b100000000 :
b10100 C
1"
#254000
0"
#255000
b10000000000 ;
b1000000000 :
b10101 C
1"
#256000
0"
#257000
b100000000000 ;
b10000000000 :
b10110 C
1"
#258000
0"
#259000
b1000000000000 ;
b100000000000 :
b10111 C
1"
#260000
0"
#261000
b10000000000000 ;
b1000000000000 :
b11000 C
1"
#262000
0"
#263000
b100000000000000 ;
b10000000000000 :
b11001 C
1"
#264000
0"
#265000
b1000000000000000 ;
b100000000000000 :
b11010 C
1"
#266000
0"
#267000
b10000000000000000 ;
b1000000000000000 :
b11011 C
1"
#268000
0"
#269000
b100000000000000000 ;
b10000000000000000 :
b11100 C
1"
#270000
0"
#271000
b1000000000000000000 ;
b100000000000000000 :
b11101 C
1"
#272000
0"
#273000
b1 @
b111011001001001010 ;
b1000000000000000000 :
b11110 C
1"
#274000
0"
#275000
b11 @
b110001011011011110 ;
b111011001001001010 :
b1 ?
b11111 C
1"
#276000
0"
#277000
b111 @
b11110000000000110 ;
b110001011011011110 :
b11 ?
b100000 C
1"
#278000
0"
#279000
b111100000000001100 ;
b1110 @
b11110000000000110 :
b111 ?
b100001 C
1"
#280000
0"
#281000
b11101 @
b110011001001100010 ;
b111100000000001100 :
b1110 ?
b100010 C
1"
#282000
0"
#283000
b111011 @
b100001011100001110 ;
b110011001001100010 :
b11101 ?
b100011 C
1"
#284000
0"
#285000
b1000010111000011100 ;
b1110110 @
b100001011100001110 :
b111011 ?
b100100 C
1"
#286000
0"
#287000
b11101101 @
b1000000111010000010 ;
b1000010111000011100 :
b1110110 ?
b100101 C
1"
#288000
0"
#289000
b111011011 @
b111100111101001110 ;
b1000000111010000010 :
b11101101 ?
b100110 C
1"
#290000
0"
#291000
b1110110111 @
b110101000011100110 ;
b111100111101001110 :
b111011011 ?
b100111 C
1"
#292000
0"
#293000
b11101101111 @
b100101010000010110 ;
b110101000011100110 :
b1110110111 ?
b101000 C
1"
#294000
0"
#295000
b111011011111 @
b101101001110110 ;
b100101010000010110 :
b11101101111 ?
b101001 C
1"
#296000
0"
#297000
b1011010011101100 ;
b1110110111110 @
b101101001110110 :
b111011011111 ?
b101010 C
1"
#298000
0"
#299000
b10110100111011000 ;
b11101101111100 @
b1011010011101100 :
b1110110111110 ?
b101011 C
1"
#300000
0"
#301000
b101101001110110000 ;
b111011011111000 @
b10110100111011000 :
b11101101111100 ?
b101100 C
1"
#302000
0"
#303000
b1110110111110001 @
b10101100110101010 ;
b101101001110110000 :
b111011011111000 ?
b101101 C
1"
#304000
0"
#305000
b101011001101010100 ;
b11101101111100010 @
b10101100110101010 :
b1110110111110001 ?
b101110 C
1"
#306000
0"
#307000
b100000000101011110 (
b1000000001010111101 '
b1000000001010111101 1
b1000000001010111101 3
b11101101111100010 *
b11101101111100010 2
b11101101111100010 A
0<
1&
1"
#308000
0"
#309000
b11110111010100000 (
b111101110101000000 '
b111101110101000000 1
b111101110101000000 3
b100000000101011110 6
b101 /
b100000000101011110 )
b100000000101011110 +
b100000000101011110 0
b100000000101011110 5
1"
#310000
0"
#311000
b11110010101000001 (
b111100101010000010 '
b111100101010000010 1
b111100101010000010 3
b11110111010100000 6
b0 ;
b100000000000000000000 @
b110 /
b11110111010100000 )
b11110111010100000 +
b11110111010100000 0
b11110111010100000 5
1<
b0 :
b10000000000000000000 ?
0&
b0 C
b100000000101011110 >
1"
#312000
0"
#313000
b11110111010100000 >
1"
#314000
0"
#315000
b1000000000000000000000 @
b100000000000000000000 ?
b1 C
1"
#316000
0"
#317000
b10000000000000000000000 @
b1000000000000000000000 ?
b10 C
1"
#318000
0"
#319000
b100000000000000000000000 @
b10000000000000000000000 ?
b11 C
1"
#320000
0"
#321000
b1000000000000000000000000 @
b100000000000000000000000 ?
b100 C
1"
#322000
0"
#323000
b10000000000000000000000000 @
b1000000000000000000000000 ?
b101 C
1"
#324000
0"
#325000
b100000000000000000000000000 @
b10000000000000000000000000 ?
b110 C
1"
#326000
0"
#327000
b1000000000000000000000000000 @
b100000000000000000000000000 ?
b111 C
1"
#328000
0"
#329000
b10000000000000000000000000000 @
b1000000000000000000000000000 ?
b1000 C
1"
#330000
0"
#331000
b100000000000000000000000000000 @
b10000000000000000000000000000 ?
b1001 C
1"
#332000
0"
#333000
b1000000000000000000000000000000 @
b100000000000000000000000000000 ?
b1010 C
1"
#334000
0"
#335000
b1 ;
b0 @
b1000000000000000000000000000000 ?
b1011 C
1"
#336000
0"
#337000
b10 ;
b1 :
b0 ?
b1100 C
1"
#338000
0"
#339000
b100 ;
b10 :
b1101 C
1"
#340000
0"
#341000
b1000 ;
b100 :
b1110 C
1"
#342000
0"
#343000
b10000 ;
b1000 :
b1111 C
1"
#344000
0"
#345000
b100000 ;
b10000 :
b10000 C
1"
#346000
0"
#347000
b1000000 ;
b100000 :
b10001 C
1"
#348000
0"
#349000
b10000000 ;
b1000000 :
b10010 C
1"
#350000
0"
#351000
b100000000 ;
b10000000 :
b10011 C
1"
#352000
0"
#353000
b1000000000 ;
b100000000 :
b10100 C
1"
#354000
0"
#355000
b10000000000 ;
b1000000000 :
b10101 C
1"
#356000
0"
#357000
b100000000000 ;
b10000000000 :
b10110 C
1"
#358000
0"
#359000
b1000000000000 ;
b100000000000 :
b10111 C
1"
#360000
0"
#361000
b10000000000000 ;
b1000000000000 :
b11000 C
1"
#362000
0"
#363000
b100000000000000 ;
b10000000000000 :
b11001 C
1"
#364000
0"
#365000
b1000000000000000 ;
b100000000000000 :
b11010 C
1"
#366000
0"
#367000
b10000000000000000 ;
b1000000000000000 :
b11011 C
1"
#368000
0"
#369000
b100000000000000000 ;
b10000000000000000 :
b11100 C
1"
#370000
0"
#371000
b1 @
b10001011000000 ;
b100000000000000000 :
b11101 C
1"
#372000
0"
#373000
b100010110000000 ;
b10 @
b10001011000000 :
b1 ?
b11110 C
1"
#374000
0"
#375000
b1000101100000000 ;
b100 @
b100010110000000 :
b10 ?
b11111 C
1"
#376000
0"
#377000
b10001011000000000 ;
b1000 @
b1000101100000000 :
b100 ?
b100000 C
1"
#378000
0"
#379000
b100010110000000000 ;
b10000 @
b10001011000000000 :
b1000 ?
b100001 C
1"
#380000
0"
#381000
b100001 @
b111101011000000 ;
b100010110000000000 :
b10000 ?
b100010 C
1"
#382000
0"
#383000
b1111010110000000 ;
b1000010 @
b111101011000000 :
b100001 ?
b100011 C
1"
#384000
0"
#385000
b11110101100000000 ;
b10000100 @
b1111010110000000 :
b1000010 ?
b100100 C
1"
#386000
0"
#387000
b111101011000000000 ;
b100001000 @
b11110101100000000 :
b10000100 ?
b100101 C
1"
#388000
0"
#389000
b1000010001 @
b111100111011000000 ;
b111101011000000000 :
b100001000 ?
b100110 C
1"
#390000
0"
#391000
b10000100011 @
b111100000001000000 ;
b111100111011000000 :
b1000010001 ?
b100111 C
1"
#392000
0"
#393000
b100001000111 @
b111010001101000000 ;
b111100000001000000 :
b10000100011 ?
b101000 C
1"
#394000
0"
#395000
b1000010001111 @
b110110100101000000 ;
b111010001101000000 :
b100001000111 ?
b101001 C
1"
#396000
0"
#397000
b10000100011111 @
b101111010101000000 ;
b110110100101000000 :
b1000010001111 ?
b101010 C
1"
#398000
0"
#399000
b100001000111111 @
b100000110101000000 ;
b101111010101000000 :
b10000100011111 ?
b101011 C
1"
#400000
0"
#401000
b1000010001111111 @
b11110101000000 ;
b100000110101000000 :
b100001000111111 ?
b101100 C
1"
#402000
0"
#403000
b111101010000000 ;
b10000100011111110 @
b11110101000000 :
b1000010001111111 ?
b101101 C
1"
#404000
0"
#405000
b1111010100000000 ;
b100001000111111100 @
b111101010000000 :
b10000100011111110 ?
b101110 C
1"
#406000
0"
#407000
b100000000001001110 (
b1000000000010011100 '
b1000000000010011100 1
b1000000000010011100 3
b100001000111111100 *
b100001000111111100 2
b100001000111111100 A
0<
1&
1"
#408000
0"
#409000
b100000100100100101 (
b1000001001001001010 '
b1000001001001001010 1
b1000001001001001010 3
b100000000001001110 6
b111 /
b100000000001001110 )
b100000000001001110 +
b100000000001001110 0
b100000000001001110 5
1"
#410000
0"
#411000
b100000110110010000 (
b1000001101100100001 '
b1000001101100100001 1
b1000001101100100001 3
b100000100100100101 6
b0 ;
b100000000000000000000 @
b1000 /
b100000100100100101 )
b100000100100100101 +
b100000100100100101 0
b100000100100100101 5
1<
b0 :
b10000000000000000000 ?
0&
b0 C
b100000000001001110 >
1"
#412000
0"
#413000
b100000100100100101 >
1"
#414000
0"
#415000
b1000000000000000000000 @
b100000000000000000000 ?
b1 C
1"
#416000
0"
#417000
b10000000000000000000000 @
b1000000000000000000000 ?
b10 C
1"
#418000
0"
#419000
b100000000000000000000000 @
b10000000000000000000000 ?
b11 C
1"
#420000
0"
#421000
b1000000000000000000000000 @
b100000000000000000000000 ?
b100 C
1"
#422000
0"
#423000
b10000000000000000000000000 @
b1000000000000000000000000 ?
b101 C
1"
#424000
0"
#425000
b100000000000000000000000000 @
b10000000000000000000000000 ?
b110 C
1"
#426000
0"
#427000
b1000000000000000000000000000 @
b100000000000000000000000000 ?
b111 C
1"
#428000
0"
#429000
b10000000000000000000000000000 @
b1000000000000000000000000000 ?
b1000 C
1"
#430000
0"
#431000
b100000000000000000000000000000 @
b10000000000000000000000000000 ?
b1001 C
1"
#432000
0"
#433000
b1000000000000000000000000000000 @
b100000000000000000000000000000 ?
b1010 C
1"
#434000
0"
#435000
b1 ;
b0 @
b1000000000000000000000000000000 ?
b1011 C
1"
#436000
0"
#437000
b10 ;
b1 :
b0 ?
b1100 C
1"
#438000
0"
#439000
b100 ;
b10 :
b1101 C
1"
#440000
0"
#441000
b1000 ;
b100 :
b1110 C
1"
#442000
0"
#443000
b10000 ;
b1000 :
b1111 C
1"
#444000
0"
#445000
b100000 ;
b10000 :
b10000 C
1"
#446000
0"
#447000
b1000000 ;
b100000 :
b10001 C
1"
#448000
0"
#449000
b10000000 ;
b1000000 :
b10010 C
1"
#450000
0"
#451000
b100000000 ;
b10000000 :
b10011 C
1"
#452000
0"
