user/src/basic/xita_tan_lut.v
//θ-tanθ查找表模块
//输入：i（tanθ=1/2^i）（迭代次数）
//输出：θ（角度值）
//功能：输入1/2^i即tanθ，输出θ（角度值）
`ifndef XITA_TAN_LUT_V
`define XITA_TAN_LUT_V
module xita_tan_lut(
    input clk,
    input [4:0]i,
    output reg [31:0] xita
);
    
    always @(negedge clk) 
    begin
        case(i)
        0: begin
            xita[31:16]=45;
            xita[15:0]=0;
        end
        1: begin
            xita[31:16]=26;
            xita[15:0]=37031;
        end
        2: begin
            xita[31:16]=14;
            xita[15:0]=2375;
        end
        3: begin
            xita[30:16]=7;
            xita[15:0]=8193;
        end
        4: begin
            xita[31:16]=3;
            xita[15:0]=37770;
        end
        5: begin
            xita[31:16]=1;
            xita[15:0]=51767;
        end
        6: begin
            xita[31:16]=0;
            xita[15:0]=58666;
        end
        7: begin
            xita[31:16]=0;
            xita[15:0]=29334;
        end
        8: begin
            xita[31:16]=0;
            xita[15:0]=14667;
        end
        9: begin
            xita[31:16]=0;
            xita[15:0]=7333;
        end
        10: begin
            xita[31:16]=0;
            xita[15:0]=3666;
        end
        11: begin
            xita[31:16]=0;
            xita[15:0]=1833;
        end
        12: begin
            xita[31:16]=0;
            xita[15:0]=916;
        end
        13: begin
            xita[31:16]=0;
            xita[15:0]=458;
        end
        14: begin
            xita[31:16]=0;
            xita[15:0]=229;
        end
        15: begin
            xita[31:16]=0;
            xita[15:0]=114;
        end
        16: begin
            xita[31:16]=0;
            xita[15:0]=57;
        end
        17: begin
            xita[31:16]=0;
            xita[15:0]=28;
        end
        18: begin
            xita[31:16]=0;
            xita[15:0]=14;
        end
        19: begin
            xita[31:16]=0;
            xita[15:0]=7;
        end
        20: begin
            xita[31:16]=0;
            xita[15:0]=4;
        end
        default : xita=0;    
        endcase
    end

endmodule
`endif

user/src/basic/qdiv.v
`ifndef QDIV_V
`define QDIV_V

module qdiv(
    input clk,
    input rst_n,
    input [31:0] dividend,
    input [31:0] divisor,
    output reg [31:0] quotient,
    output reg valid,//运算完成信号
    output reg warn,//除数为0警告
    output reg busy//运算中信号
    );

    parameter WIDTH = 31;
    parameter  FBITS = 16;

  integer i=0;

    reg [WIDTH-1:0] dividend_reg;//被除数寄存器(不带符号)
    reg [WIDTH-1:0] divisor_reg;//除数寄存器(不带符号)
    reg [WIDTH:0] acc;//单次被除数
    reg [WIDTH-1:0] quo;//实际使用中移位的被除数和商(复用)

    reg [WIDTH:0] acc_next;//单次被除数下一个
    reg [WIDTH-1:0] quo_next;//实际使用中移位的被除数下一个

  always @(*) 
  begin
    if (acc >= {1'b0, divisor_reg}) 
    begin
      acc_next = acc - divisor_reg;
      {acc_next, quo_next} = {acc_next[WIDTH-1:0], quo, 1'b1};
    end 
    else 
    begin
      {acc_next, quo_next} = {acc, quo} << 1;
    end
  end

    always @(negedge clk or negedge rst_n) 
    begin
        if(!rst_n)
        begin
            dividend_reg <= 0;
            divisor_reg <= 0;
            quotient <= 0;
            valid <= 0;
            warn <= 0;
            acc <= 0;
            quo <= 0;
        end
        else if(divisor==0)
        begin
            warn <= 1;
            valid <= 0;
            quotient <= 0;
            busy <= 0;
        end
        else
        begin
            dividend_reg <= dividend;
            divisor_reg <= divisor;
            if(dividend!=dividend_reg||divisor!=divisor_reg)//输入变化，重新计算
            begin
                i <= 0;
                valid <= 0;
                {acc, quo} <= {{WIDTH{1'b0}}, dividend, 1'b0};
                busy <= 1'b1;
            end
            else
            begin
                if(i==WIDTH+FBITS-1)
                begin
                    valid<=1;
                    quotient<=quo_next[WIDTH-1:0];
                    busy <= 1'b0;
                end
                else
                begin
                    i<=i+1;
                    {acc, quo} <= {acc_next, quo_next};
                end
            end
        end
    end
endmodule
`endif

user/src/basic/tan.v
`ifndef TAN_V
`define TAN_V
//`include "../arctan/xita_tan_lut.v"
//`include "../qdiv/qdiv.v"
module tan(
    input clk,
    input rst_n,
    output reg valid,

    input [31:0] xita,
    output reg [31:0] tan
);

    parameter K=39796;

    wire valid_div;
    wire [31:0] tan_c;//当前正切值
    wire [31:0] xita_c;//当前旋转角

    reg [31:0] x;
    reg [31:0] y;
    reg [31:0] z;
    reg [31:0] xita_reg;
    reg [1:0] cnt;

    integer i=0;

    qdiv 
    qdiv_dut (
        .clk (clk ),
        .rst_n (rst_n ),
        .valid ( valid_div),
        .dividend (y ),
        .divisor (x ),
        .quotient (tan_c ),
        .warn ( ),
        .busy ( )
    );
    xita_tan_lut 
    xita_tan_lut_dut (
        .clk(clk ),
        .i (i ),
        .xita  ( xita_c)
    );

    always @(negedge clk or negedge rst_n) 
    begin
        if(!rst_n)
        begin
            valid<=0;
            x<=0;
            y<=0;
            z<=0;
            i<=0;
            xita_reg<=xita;
            tan<=0;
        end
        else
        begin
            xita_reg<=xita;
            if(xita_reg!=xita)
            begin
                i<=0;
                x<=K;
                y<=0;
                z<=0;
                valid<=0;
                cnt<=0;
            end
            else
            begin
                if(i==20)
                begin
                    valid<=1;
                    tan<=tan_c;
                    cnt<=0;
                end
                else
                begin
                    if(valid_div==1)
                    begin
                       cnt<=cnt+1;
                    end
                    else
                    begin
                        cnt<=0;
                    end
                    if(valid_div==1 && cnt==2)
                    begin
                        i<=i+1;
                        if(z<xita)
                        begin
                            z<=z+xita_c;
                            x<=x-(y>>i);
                            y<=y+(x>>i);
                        end
                        else if(z>xita)
                        begin
                            z<=z-xita_c;
                            x<=x+(y>>i);
                            y<=y-(x>>i);
                        end
                        else
                        begin
                            z<=z;
                            x<=x;
                            y<=y;
                        end
                    end
                end
            end
        end      
    end

endmodule
`endif

user/sim/basic/tan_tb.v
`timescale 1ns/1ps
module tan_tb;

// Parameters
localparam  K = 39796;

// Ports
reg clk = 0;
reg rst_n = 0;
wire valid;
reg [31:0] xita;
wire [31:0] tan;

tan 
#(
  .K (
      K )
)
tan_dut (
  .clk (clk ),
  .rst_n (rst_n ),
  .valid (valid ),
  .xita (xita ),
  .tan  ( tan)
);

initial begin
  begin
      $dumpfile("tan_tb.vcd");
      $dumpvars(0,tan_tb);
      rst_n=1;
      //xita=32'h0000_0000;
      #10
      rst_n=0;
      #10
      rst_n=1;
      #10
      xita=32'h001E_0000;
      #10000
      xita=32'h0000_0000;
      #10000
      xita=32'h003C_0000;
      #10000
      xita=32'h002D_0000;
      #10000
    $finish;
  end
end

always
  #1  clk = ! clk ;

endmodule

tan_tb.vcd
$date
	Fri Jun 30 21:16:58 2023
$end
$version
	Icarus Verilog
$end
$timescale
	1ps
$end
$scope module tan_tb $end
$var wire 1 ! valid $end
$var wire 32 " tan [31:0] $end
$var parameter 32 # K $end
$var reg 1 $ clk $end
$var reg 1 % rst_n $end
$var reg 32 & xita [31:0] $end
$scope module tan_dut $end
$var wire 1 $ clk $end
$var wire 1 % rst_n $end
$var wire 32 ' xita [31:0] $end
$var wire 32 ( xita_c [31:0] $end
$var wire 1 ) valid_div $end
$var wire 32 * tan_c [31:0] $end
$var parameter 32 + K $end
$var reg 2 , cnt [1:0] $end
$var reg 32 - tan [31:0] $end
$var reg 1 ! valid $end
$var reg 32 . x [31:0] $end
$var reg 32 / xita_reg [31:0] $end
$var reg 32 0 y [31:0] $end
$var reg 32 1 z [31:0] $end
$var integer 32 2 i [31:0] $end
$scope module qdiv_dut $end
$var wire 1 $ clk $end
$var wire 32 3 dividend [31:0] $end
$var wire 32 4 divisor [31:0] $end
$var wire 1 % rst_n $end
$var parameter 32 5 FBITS $end
$var parameter 32 6 WIDTH $end
$var reg 32 7 acc [31:0] $end
$var reg 32 8 acc_next [31:0] $end
$var reg 1 9 busy $end
$var reg 31 : dividend_reg [30:0] $end
$var reg 31 ; divisor_reg [30:0] $end
$var reg 31 < quo [30:0] $end
$var reg 31 = quo_next [30:0] $end
$var reg 32 > quotient [31:0] $end
$var reg 1 ) valid $end
$var reg 1 ? warn $end
$var integer 32 @ i [31:0] $end
$upscope $end
$scope module xita_tan_lut_dut $end
$var wire 1 $ clk $end
$var wire 5 A i [4:0] $end
$var reg 32 B xita [31:0] $end
$upscope $end
$upscope $end
$upscope $end
$enddefinitions $end
$comment Show the parameter values. $end
$dumpall
b11111 6
b10000 5
b1001101101110100 +
b1001101101110100 #
$end
#0
$dumpvars
bx B
b0 A
b0 @
x?
bx >
bx =
bx <
bx ;
bx :
x9
bx 8
bx 7
bx 4
bx 3
b0 2
bx 1
bx 0
bx /
bx .
bx -
bx ,
bx *
x)
bx (
bx '
bx &
1%
0$
bx "
x!
$end
#1000
1$
#2000
b1 @
b0 ,
b1011010000000000000000 (
b1011010000000000000000 B
0$
#3000
1$
#4000
b10 @
0$
#5000
1$
#6000
b11 @
0$
#7000
1$
#8000
b100 @
0$
#9000
1$
#10000
b1 =
b0 8
b0 <
b0 7
0?
0)
b0 *
b0 >
b0 ;
b0 :
b0 "
b0 -
b0 1
b0 0
b0 3
b0 .
b0 4
0!
0$
0%
#11000
1$
#12000
0$
#13000
1$
#14000
0$
#15000
1$
#16000
0$
#17000
1$
#18000
0$
#19000
1$
#20000
09
1?
0$
1%
#21000
1$
#22000
0$
#23000
1$
#24000
0$
#25000
1$
#26000
0$
#27000
1$
#28000
0$
#29000
1$
#30000
b111100000000000000000 /
0$
b111100000000000000000 &
b111100000000000000000 '
