user/src/uart/uart_asc_num.v
//uart接收到的ascii码(16进制表示)转32位定点数
//输入：uart时钟clk,复位rst_n,8位ascii码asc,上升沿启动信号start，数据错误信号dataerror,帧错误信号frameerror
//输出：32位定点数xdataout,ydataout,zdataout,完成信号valid
//功能：将uart接收到的ascii码转换为32位定点数，接收8次asc码，输出一次32位定点数
module uart_asc_num(
        input clk, //uart时钟
        input rst_n, //复位信号
        input [7:0] asc, //uart接收到的ascii码
        input start, //上升沿启动信号
        input dataerror, //数据错误信号
        input frameerror, //帧错误信号
        input clr, //清零信号
        output reg [31:0] xdataout, //32位定点数输出x
        output reg [31:0] ydataout, //32位定点数输出y
        output reg [31:0] zdataout, //32位定点数输出z
        output reg valid //完成信号
    );

    reg start_prev;
    reg [4:0] cnt;
    reg startrs;//strat上升
    reg [3:0] num_16;//单个ascii码对应的4位数字

    //ascii码转换为数字
    always @(*) begin
        case(asc)
            8'd48:
                num_16 = 4'd0;
            8'd49:
                num_16 = 4'd1;
            8'd50:
                num_16 = 4'd2;
            8'd51:
                num_16 = 4'd3;
            8'd52:
                num_16 = 4'd4;
            8'd53:
                num_16 = 4'd5;
            8'd54:
                num_16 = 4'd6;
            8'd55:
                num_16 = 4'd7;
            8'd56:
                num_16 = 4'd8;
            8'd57:
                num_16 = 4'd9;
            8'd65:
                num_16 = 4'd10;
            8'd66:
                num_16 = 4'd11;
            8'd67:
                num_16 = 4'd12;
            8'd68:
                num_16 = 4'd13;
            8'd69:
                num_16 = 4'd14;
            8'd70:
                num_16 = 4'd15;
            8'd97:
                num_16 = 4'd10;
            8'd98:
                num_16 = 4'd11;
            8'd99:
                num_16 = 4'd12;
            8'd100:
                num_16 = 4'd13;
            8'd101:
                num_16 = 4'd14;
            8'd102:
                num_16 = 4'd15;
            default:
                num_16 = 4'd0;
        endcase
    end

    always @(posedge clk) begin
        start_prev <= start;
        startrs <= start & (~start_prev);
    end

    always @(posedge clk or negedge rst_n) begin
        if(!rst_n) begin
            start_prev <= start;
            xdataout <= 32'd0;
            ydataout <= 32'd0;
            zdataout <= 32'd0;
            valid <= 1'b0;
            cnt <= 5'd0;
        end
        else if(clr | dataerror | frameerror) begin
            start_prev <= start;
            xdataout <= 32'd0;
            ydataout <= 32'd0;
            zdataout <= 32'd0;
            valid <= 1'b0;
            cnt <= 5'd0;
        end
        else begin
            if(startrs & !dataerror & !frameerror) begin
                cnt <= cnt+5'b1;
                if(cnt == 5'd23)
                    cnt <= 5'b0;
                case (cnt)
                    5'd0: begin
                        xdataout[31:28] <= num_16;
                        valid <= 1'b0;
                    end
                    5'd1: begin
                        xdataout[27:24] <= num_16;
                        valid <= 1'b0;
                    end
                    5'd2: begin
                        xdataout[23:20] <= num_16;
                        valid <= 1'b0;
                    end
                    5'd3: begin
                        xdataout[19:16] <= num_16;
                        valid <= 1'b0;
                    end
                    5'd4: begin
                        xdataout[15:12] <= num_16;
                        valid <= 1'b0;
                    end
                    5'd5: begin
                        xdataout[11:8] <= num_16;
                        valid <= 1'b0;
                    end
                    5'd6: begin
                        xdataout[7:4] <= num_16;
                        valid <= 1'b0;
                    end
                    5'd7: begin
                        xdataout[3:0] <= num_16;
                        valid <= 1'b0;
                    end

                    5'd8: begin
                        ydataout[31:28] <= num_16;
                        valid <= 1'b0;
                    end
                    5'd9: begin
                        ydataout[27:24] <= num_16;
                        valid <= 1'b0;
                    end
                    5'd10: begin
                        ydataout[23:20] <= num_16;
                        valid <= 1'b0;
                    end
                    5'd11: begin
                        ydataout[19:16] <= num_16;
                        valid <= 1'b0;
                    end
                    5'd12: begin
                        ydataout[15:12] <= num_16;
                        valid <= 1'b0;
                    end
                    5'd13: begin
                        ydataout[11:8] <= num_16;
                        valid <= 1'b0;
                    end
                    5'd14: begin
                        ydataout[7:4] <= num_16;
                        valid <= 1'b0;
                    end
                    5'd15: begin
                        ydataout[3:0] <= num_16;
                        valid <= 1'b0;
                    end

                    5'd16: begin
                        zdataout[31:28] <= num_16;
                        valid <= 1'b0;
                    end
                    5'd17: begin
                        zdataout[27:24] <= num_16;
                        valid <= 1'b0;
                    end
                    5'd18: begin
                        zdataout[23:20] <= num_16;
                        valid <= 1'b0;
                    end
                    5'd19: begin
                        zdataout[19:16] <= num_16;
                        valid <= 1'b0;
                    end
                    5'd20: begin
                        zdataout[15:12] <= num_16;
                        valid <= 1'b0;
                    end
                    5'd21: begin
                        zdataout[11:8] <= num_16;
                        valid <= 1'b0;
                    end
                    5'd22: begin
                        zdataout[7:4] <= num_16;
                        valid <= 1'b0;
                    end
                    5'd23: begin
                        zdataout[3:0] <= num_16;
                        valid <= 1'b1;
                    end
                endcase
            end
        end
    end
endmodule

user/sim/uart/uart_asc_num_tb.v
`timescale 1ns/1ps
module uart_asc_num_tb;

// Parameters

// Ports
reg clk = 0;
reg rst_n = 0;
reg [7:0] asc;
reg start = 0;
reg dataerror = 0;
reg frameerror = 0;
reg clr = 0;
wire [31:0] xdataout;
wire [31:0] ydataout;
wire [31:0] zdataout;
wire valid;

uart_asc_num 
uart_asc_num_dut (
  .clk (clk ),
  .rst_n (rst_n ),
  .asc (asc ),
  .start (start ),
  .dataerror (dataerror ),
  .frameerror (frameerror ),
  .clr (clr ),
  .xdataout (xdataout ),
  .ydataout (ydataout ),
  .zdataout (zdataout ),
  .valid  ( valid)
);

  initial begin
    begin
        $dumpfile("uart_asc_num_tb.vcd");
        $dumpvars(0, uart_asc_num_tb);
        rst_n = 0;
        #10 
        rst_n = 1;
        dataerror = 0;
        frameerror = 0;
        clr = 0;
        start=0;
        #10
        asc = 8'd48;
        start = 1;
        #10
        start = 0;
        #100
        asc = 8'd48;
        start = 1;
        #10
        start = 0;
        #100
        asc = 8'd48;
        start = 1;
        #10
        start = 0;
        #100
        asc = 8'd49;
        start = 1;
        #10
        start = 0;
        #100
        asc = 8'd49;
        start = 1;
        #10
        start = 0;
        #100
        asc = 8'd49;
        start = 1;
        #10
        start = 0;
        #100
        asc = 8'd49;
        start = 1;
        #10
        start = 0;
        #100
        asc = 8'd49;
        start = 1;
        #100
        
        start=0;
        #10
        asc = 8'd49;
        start = 1;
        #10
        start = 0;
        #100
        asc = 8'd48;
        start = 1;
        #10
        start = 0;
        #100
        asc = 8'd48;
        start = 1;
        #10
        start = 0;
        #100
        asc = 8'd49;
        start = 1;
        #10
        start = 0;
        #100
        asc = 8'd49;
        start = 1;
        #10
        start = 0;
        #100
        asc = 8'd49;
        start = 1;
        #10
        start = 0;
        #100
        asc = 8'd97;
        start = 1;
        #10
        start = 0;
        #100
        asc = 8'd65;
        start = 1;
        #100
        
        start=0;
        #10
        asc = 8'd49;
        start = 1;
        #10
        start = 0;
        #100
        asc = 8'd48;
        start = 1;
        #10
        start = 0;
        #100
        asc = 8'd48;
        start = 1;
        #10
        start = 0;
        #100
        asc = 8'd49;
        start = 1;
        #10
        start = 0;
        #100
        asc = 8'd49;
        start = 1;
        #10
        start = 0;
        #100
        asc = 8'd49;
        start = 1;
        #10
        start = 0;
        #100
        asc = 8'd97;
        start = 1;
        #10
        start = 0;
        #100
        asc = 8'd65;
        start = 1;
        #100
        $finish;
    end
  end

  always
    #5  clk = ! clk ;

endmodule

uart_asc_num_tb.vcd
$date
	Tue Jul 04 21:03:21 2023
$end
$version
	Icarus Verilog
$end
$timescale
	1ps
$end
$scope module uart_asc_num_tb $end
$var wire 32 ! zdataout [31:0] $end
$var wire 32 " ydataout [31:0] $end
$var wire 32 # xdataout [31:0] $end
$var wire 1 $ valid $end
$var reg 8 % asc [7:0] $end
$var reg 1 & clk $end
$var reg 1 ' clr $end
$var reg 1 ( dataerror $end
$var reg 1 ) frameerror $end
$var reg 1 * rst_n $end
$var reg 1 + start $end
$scope module uart_asc_num_dut $end
$var wire 8 , asc [7:0] $end
$var wire 1 & clk $end
$var wire 1 ' clr $end
$var wire 1 ( dataerror $end
$var wire 1 ) frameerror $end
$var wire 1 * rst_n $end
$var wire 1 + start $end
$var reg 5 - cnt [4:0] $end
$var reg 4 . num_16 [3:0] $end
$var reg 1 / start_prev $end
$var reg 1 0 startrs $end
$var reg 1 $ valid $end
$var reg 32 1 xdataout [31:0] $end
$var reg 32 2 ydataout [31:0] $end
$var reg 32 3 zdataout [31:0] $end
$upscope $end
$upscope $end
$enddefinitions $end
$comment Show the parameter values. $end
$dumpall
$end
#0
$dumpvars
bx 3
bx 2
bx 1
x0
x/
bx .
bx -
bx ,
0+
0*
0)
0(
0'
0&
bx %
x$
bx #
bx "
bx !
$end
#5000
b0 -
0$
b0 !
b0 3
b0 "
b0 2
b0 #
b0 1
00
0/
1&
#10000
0&
1*
#15000
1&
#20000
b0 .
0&
1+
b110000 %
b110000 ,
#25000
10
1/
1&
#30000
0&
0+
#35000
b1 -
00
0/
1&
#40000
0&
#45000
1&
#50000
0&
#55000
1&
#60000
0&
#65000
1&
#70000
0&
#75000
1&
#80000
0&
#85000
1&
#90000
0&
#95000
1&
#100000
0&
#105000
1&
#110000
0&
#115000
1&
#120000
0&
#125000
1&
#130000
0&
1+
#135000
10
1/
1&
#140000
0&
0+
#145000
b10 -
00
0/
1&
#150000
0&
#155000
1&
#160000
0&
#165000
1&
#170000
0&
#175000
1&
#180000
0&
#185000
1&
#190000
0&
#195000
1&
#200000
0&
#205000
1&
#210000
0&
#215000
1&
#220000
0&
#225000
1&
#230000
0&
#235000
1&
#240000
0&
1+
#245000
10
1/
1&
#250000
0&
0+
#255000
b11 -
00
0/
1&
#260000
0&
#265000
1&
#270000
0&
#275000
1&
#280000
0&
#285000
1&
#290000
0&
#295000
1&
#300000
0&
#305000
1&
#310000
0&
#315000
1&
#320000
0&
#325000
1&
#330000
0&
#335000
1&
#340000
0&
#345000
1&
#350000
b1 .
0&
1+
b110001 %
b110001 ,
#355000
10
1/
1&
#360000
0&
0+
#365000
b10000000000000000 #
b10000000000000000 1
b100 -
00
0/
1&
#370000
0&
#375000
1&
#380000
0&
#385000
1&
#390000
0&
#395000
1&
#400000
0&
#405000
1&
#410000
0&
#415000
1&
#420000
0&
#425000
1&
#430000
0&
#435000
1&
#440000
0&
#445000
1&
#450000
0&
#455000
1&
#460000
0&
1+
#465000
10
1/
1&
#470000
0&
0+
#475000
b10001000000000000 #
b10001000000000000 1
b101 -
00
0/
1&
#480000
0&
#485000
1&
#490000
0&
#495000
1&
#500000
0&
#505000
1&
#510000
0&
#515000
1&
#520000
0&
#525000
1&
#530000
0&
#535000
1&
#540000
0&
#545000
1&
#550000
0&
#555000
1&
#560000
0&
#565000
1&
#570000
0&
1+
#575000
10
1/
1&
#580000
0&
0+
#585000
b10001000100000000 #
b10001000100000000 1
b110 -
00
0/
1&
#590000
0&
#595000
1&
#600000
0&
#605000
1&
#610000
0&
#615000
1&
#620000
0&
#625000
1&
#630000
0&
#635000
1&
#640000
0&
#645000
1&
#650000
0&
#655000
1&
#660000
0&
#665000
1&
#670000
0&
#675000
1&
#680000
0&
1+
#685000
10
1/
1&
#690000
0&
0+
#695000
b10001000100010000 #
b10001000100010000 1
b111 -
00
0/
1&
#700000
0&
#705000
1&
#710000
0&
#715000
1&
#720000
0&
#725000
1&
#730000
0&
#735000
1&
#740000
0&
#745000
1&
#750000
0&
#755000
1&
#760000
0&
#765000
1&
#770000
0&
#775000
1&
#780000
0&
#785000
1&
#790000
0&
1+
#795000
10
1/
1&
#800000
0&
#805000
b10001000100010001 #
b10001000100010001 1
b1000 -
00
1&
#810000
0&
#815000
1&
#820000
0&
#825000
1&
#830000
0&
#835000
1&
#840000
0&
#845000
1&
#850000
0&
#855000
1&
#860000
0&
#865000
1&
#870000
0&
#875000
1&
#880000
0&
#885000
1&
#890000
0&
0+
#895000
0/
1&
#900000
0&
1+
#905000
10
1/
1&
#910000
0&
0+
#915000
b10000000000000000000000000000 "
b10000000000000000000000000000 2
b1001 -
00
0/
1&
#920000
0&
#925000
1&
#930000
0&
#935000
1&
#940000
0&
#945000
1&
#950000
0&
#955000
1&
#960000
0&
#965000
1&
#970000
0&
#975000
1&
#980000
0&
#985000
1&
#990000
0&
#995000
1&
#1000000
0&
#1005000
1&
#1010000
b0 .
0&
1+
b110000 %
b110000 ,
#1015000
10
1/
1&
#1020000
0&
0+
#1025000
b1010 -
00
0/
1&
#1030000
0&
#1035000
1&
#1040000
0&
#1045000
1&
#1050000
0&
#1055000
1&
#1060000
0&
#1065000
1&
#1070000
0&
#1075000
1&
#1080000
0&
#1085000
1&
#1090000
0&
#1095000
1&
#1100000
0&
#1105000
1&
#1110000
0&
#1115000
1&
#1120000
0&
1+
#1125000
10
1/
1&
#1130000
0&
0+
#1135000
b1011 -
00
0/
1&
#1140000
0&
#1145000
1&
#1150000
0&
#1155000
1&
#1160000
0&
#1165000
1&
#1170000
0&
#1175000
1&
#1180000
0&
#1185000
1&
#1190000
0&
#1195000
1&
#1200000
0&
#1205000
1&
#1210000
0&
#1215000
1&
#1220000
0&
#1225000
1&
#1230000
b1 .
0&
1+
b110001 %
b110001 ,
#1235000
10
1/
1&
#1240000
0&
0+
#1245000
b10000000000010000000000000000 "
b10000000000010000000000000000 2
b1100 -
00
0/
1&
#1250000
0&
#1255000
1&
#1260000
0&
#1265000
1&
#1270000
0&
#1275000
1&
#1280000
0&
#1285000
1&
#1290000
0&
#1295000
1&
#1300000
0&
#1305000
1&
#1310000
0&
#1315000
1&
#1320000
0&
#1325000
1&
#1330000
0&
#1335000
1&
#1340000
0&
1+
#1345000
10
1/
1&
#1350000
0&
0+
#1355000
b10000000000010001000000000000 "
b10000000000010001000000000000 2
b1101 -
00
0/
1&
#1360000
0&
#1365000
1&
#1370000
0&
#1375000
1&
#1380000
0&
#1385000
1&
#1390000
0&
#1395000
1&
#1400000
0&
#1405000
1&
#1410000
0&
#1415000
1&
#1420000
0&
#1425000
1&
#1430000
0&
#1435000
1&
#1440000
0&
#1445000
1&
#1450000
0&
1+
#1455000
10
1/
1&
#1460000
0&
0+
#1465000
b10000000000010001000100000000 "
b10000000000010001000100000000 2
b1110 -
00
0/
1&
#1470000
0&
#1475000
1&
#1480000
0&
#1485000
1&
#1490000
0&
#1495000
1&
#1500000
0&
#1505000
1&
#1510000
0&
#1515000
1&
#1520000
0&
#1525000
1&
#1530000
0&
#1535000
1&
#1540000
0&
#1545000
1&
#1550000
0&
#1555000
1&
#1560000
b1010 .
0&
1+
b1100001 %
b1100001 ,
#1565000
10
1/
1&
#1570000
0&
0+
#1575000
b10000000000010001000110100000 "
b10000000000010001000110100000 2
b1111 -
00
0/
1&
#1580000
0&
#1585000
1&
#1590000
0&
#1595000
1&
#1600000
0&
#1605000
1&
#1610000
0&
#1615000
1&
#1620000
0&
#1625000
1&
#1630000
0&
#1635000
1&
#1640000
0&
#1645000
1&
#1650000
0&
#1655000
1&
#1660000
0&
#1665000
1&
#1670000
0&
1+
b1000001 %
b1000001 ,
#1675000
10
1/
1&
#1680000
0&
#1685000
b10000000000010001000110101010 "
b10000000000010001000110101010 2
b10000 -
00
1&
#1690000
0&
#1695000
1&
#1700000
0&
#1705000
1&
#1710000
0&
#1715000
1&
#1720000
0&
#1725000
1&
#1730000
0&
#1735000
1&
#1740000
0&
#1745000
1&
#1750000
0&
#1755000
1&
#1760000
0&
#1765000
1&
#1770000
0&
0+
#1775000
0/
1&
#1780000
b1 .
0&
1+
b110001 %
b110001 ,
#1785000
10
1/
1&
#1790000
0&
0+
#1795000
b10000000000000000000000000000 !
b10000000000000000000000000000 3
b10001 -
00
0/
1&
#1800000
0&
#1805000
1&
#1810000
0&
#1815000
1&
#1820000
0&
#1825000
1&
#1830000
0&
#1835000
1&
#1840000
0&
#1845000
1&
#1850000
0&
#1855000
1&
#1860000
0&
#1865000
1&
#1870000
0&
#1875000
1&
#1880000
0&
#1885000
1&
#1890000
b0 .
0&
1+
b110000 %
b110000 ,
#1895000
10
1/
1&
#1900000
0&
0+
#1905000
b10010 -
00
0/
1&
#1910000
0&
#1915000
1&
#1920000
0&
#1925000
1&
#1930000
0&
#1935000
1&
#1940000
0&
#1945000
1&
#1950000
0&
#1955000
1&
#1960000
0&
#1965000
1&
#1970000
0&
#1975000
1&
#1980000
0&
#1985000
1&
#1990000
0&
#1995000
1&
#2000000
0&
1+
#2005000
10
1/
1&
#2010000
0&
0+
#2015000
b10011 -
00
0/
1&
#2020000
0&
#2025000
1&
#2030000
0&
#2035000
1&
#2040000
0&
#2045000
1&
#2050000
0&
#2055000
1&
#2060000
0&
#2065000
1&
#2070000
0&
#2075000
1&
#2080000
0&
#2085000
1&
#2090000
0&
#2095000
1&
#2100000
0&
#2105000
1&
#2110000
b1 .
0&
1+
b110001 %
b110001 ,
#2115000
10
1/
1&
#2120000
0&
0+
#2125000
b10000000000010000000000000000 !
b10000000000010000000000000000 3
b10100 -
00
0/
1&
#2130000
0&
#2135000
1&
#2140000
0&
#2145000
1&
#2150000
0&
#2155000
1&
#2160000
0&
#2165000
1&
#2170000
0&
#2175000
1&
#2180000
0&
#2185000
1&
#2190000
0&
#2195000
1&
#2200000
0&
#2205000
1&
#2210000
0&
#2215000
1&
#2220000
0&
1+
#2225000
10
1/
1&
#2230000
0&
0+
#2235000
b10000000000010001000000000000 !
b10000000000010001000000000000 3
b10101 -
00
0/
1&
#2240000
0&
#2245000
1&
#2250000
0&
#2255000
1&
#2260000
0&
#2265000
1&
#2270000
0&
#2275000
1&
#2280000
0&
#2285000
1&
#2290000
0&
#2295000
1&
#2300000
0&
#2305000
1&
#2310000
0&
#2315000
1&
#2320000
0&
#2325000
1&
#2330000
0&
1+
#2335000
10
1/
1&
#2340000
0&
0+
#2345000
b10000000000010001000100000000 !
b10000000000010001000100000000 3
b10110 -
00
0/
1&
#2350000
0&
#2355000
1&
#2360000
0&
#2365000
1&
#2370000
0&
#2375000
1&
#2380000
0&
#2385000
1&
#2390000
0&
#2395000
1&
#2400000
0&
#2405000
1&
#2410000
0&
#2415000
1&
#2420000
0&
#2425000
1&
#2430000
0&
#2435000
1&
#2440000
b1010 .
0&
1+
b1100001 %
b1100001 ,
#2445000
10
1/
1&
#2450000
0&
0+
#2455000
b10000000000010001000110100000 !
b10000000000010001000110100000 3
b10111 -
00
0/
1&
#2460000
0&
#2465000
1&
#2470000
0&
#2475000
1&
#2480000
0&
#2485000
1&
#2490000
0&
#2495000
1&
#2500000
0&
#2505000
1&
#2510000
0&
#2515000
1&
#2520000
0&
#2525000
1&
#2530000
0&
#2535000
1&
#2540000
0&
#2545000
1&
#2550000
0&
1+
b1000001 %
b1000001 ,
#2555000
10
1/
1&
#2560000
0&
#2565000
1$
b10000000000010001000110101010 !
b10000000000010001000110101010 3
b0 -
00
1&
