user/src/basic/xita_to_duty.v
//角度->占空比转换
//输入：32位定点数角度xita[31:0]
//输出：20位占空比duty[19:0]
//功能：根据给定的角度输出对应的占空比
module xita_to_duty(
    input [31:0] xita,
    output reg [19:0] duty
);
    wire [50:0] temp;

    assign temp=xita[30:0]*50_000/(90*65536);

    always @(*) 
    begin
        if(xita[31]==1'b0)
        begin
            if(xita[31:0]<=32'h005A_0000)
                duty=75_000+temp[19:0];
            else
                duty=125_000;
        end
        else //if(xita[31]==1'b1)
        begin
            if({1'b0,xita[30:0]}<=32'h005A_0000)
                duty=75_000-temp[19:0];
            else
                duty=25_000;
        end
    end
endmodule

user/sim/basic/xita_to_duty_tb.v
//`include "xita_to_duty.v"
`timescale 1ns/1ps
module xita_to_duty_tb;

  // Parameters

  // Ports
  reg [31:0] xita;
  wire [19:0] duty;

  xita_to_duty 
  xita_to_duty_dut (
    .xita (xita ),
    .duty  ( duty)
  );

  initial begin
    begin
        $dumpfile("xita_to_duty_tb.vcd");
        $dumpvars(0, xita_to_duty_tb);
        xita=32'h0000_0000;
        #100
        xita=32'h002D_0000;
        #100
        xita=32'h0000_0000;
        #100
        xita=32'h005A_0000;
        #100
        xita=32'h0060_0000;
        #100
        xita=32'h8064_0000;
        #100
        xita=32'h802D_0000;
        #100
        xita=32'h805A_0000;
        #100
      $finish;
    end
  end


endmodule

xita_to_duty_tb.vcd
$date
	Mon Jul 03 15:45:03 2023
$end
$version
	Icarus Verilog
$end
$timescale
	1ps
$end
$scope module xita_to_duty_tb $end
$var wire 20 ! duty [19:0] $end
$var reg 32 " xita [31:0] $end
$scope module xita_to_duty_dut $end
$var wire 32 # xita [31:0] $end
$var wire 51 $ temp [50:0] $end
$var reg 20 % duty [19:0] $end
$upscope $end
$upscope $end
$enddefinitions $end
$comment Show the parameter values. $end
$dumpall
$end
#0
$dumpvars
b10010010011111000 %
b0 $
b0 #
b0 "
b10010010011111000 !
$end
#100000
b11000011010100000 !
b11000011010100000 %
b110000110101000 $
b1011010000000000000000 "
b1011010000000000000000 #
#200000
b10010010011111000 !
b10010010011111000 %
b0 $
b0 "
b0 #
#300000
b11110100001001000 !
b11110100001001000 %
b1100001101010000 $
b10110100000000000000000 "
b10110100000000000000000 #
#400000
b1101000001010101 $
b11000000000000000000000 "
b11000000000000000000000 #
#500000
b110000110101000 !
b110000110101000 %
b1101100100000011 $
b10000000011001000000000000000000 "
b10000000011001000000000000000000 #
#600000
b1100001101010000 !
b1100001101010000 %
b110000110101000 $
b10000000001011010000000000000000 "
b10000000001011010000000000000000 #
#700000
b110000110101000 !
b110000110101000 %
b1100001101010000 $
b10000000010110100000000000000000 "
b10000000010110100000000000000000 #
